Workbook

Sheet README
A1: creatives.exchange — 3-year budget model (S / M / L scenarios)
A2: Built 2026-08-28. Prices verified against official pricing pages 2026-08-28 (LiveKit numbers re-checked 2026-08-13 in docs/phase-1b/video-provider-research.md).
A4: HOW TO USE
A5: Blue cells are inputs — change them and everything recalculates. Yellow cells are the assumptions that most change the answer.
A6: Green cells pull from the Inputs sheet. Black cells are formulas — don't type over them.
A7: Sheets: Sweat Equity (time already invested) · Inputs (unit prices) · S, M, L (scenarios) · Summary (side by side).
A9: THE THREE THINGS THIS MODEL SHOWS
A10: 1. Card fees eat roughly half of a 10% take when dues are billed $10 monthly (Stripe's 30¢ fixed fee is 3% of a $10 charge).
A11: The 'Platform absorbs processing' toggle on Inputs decides whether the business ever breaks even. Annual billing also roughly halves dues processing.
A12: 2. Year 1 is grant- and patron-funded in every scenario. Revenue does not cover even part-time staff until Year 2–3 at Medium scale.
A13: That is the argument for the Belmont/Lilly letter of inquiry and for patron capital — not a flaw in the plan, but it must be said out loud.
A14: 3. ~220 hours (~$38.5k at $175/hr) is already invested in the app. See Sweat Equity.

Sheet Sweat Equity
A1: Founder time invested to date (from git history, all branches: 456 commits, 26 active days, Jan 24 – Sep 2 2026)
A3: Phase | B3: Active days | C3: Est hrs/day | D3: Hours | E3: Note
A4: Jan 24–31 build sprint (original app) | B4: 7 | C4: 8.5 | D4: =B4*C4 -> 59.5 | E4: Committed 265 times
A5: Feb–Jun maintenance (scattered days) | B5: 7 | C5: 3 | D5: =B5*C5 -> 21 | E5: 41 commits
A6: Aug 6 – Sep 2 sprint (Garden → creatives.exchange) | B6: 12 | C6: 7 | D6: =B6*C6 -> 84 | E6: 150 commits
A7: Hands-on subtotal | D7: =SUM(D4:D6) -> 164.5
A8: Partner calls + prep (8+ recorded calls, Upsight) | D8: 12
A9: Planning, specs, design, directing build sessions (not in commits) | D9: 45
A10: TOTAL HOURS | D10: =D7+D8+D9 -> 221.5
A12: Hourly rate to value the time | B12: 175 | E12: Fractional senior product-engineer rate; user-set assumption
A13: Value of time invested | B13: =D10*B12 -> 38762.5
A15: Sensitivity: at $125/hr | B15: =D10*125 -> 27687.5
A16: Sensitivity: at $225/hr | B16: =D10*225 -> 49837.5
A18: Method: hours/day are estimates (blue — adjust them); commit counts and active days are measured facts from git.
A20: BEFORE 2026 — two earlier versions across ~10 years. Rows below are placeholder guesses: EDIT B and C to your memory.
A21: Era | B21: Years active | C21: Avg hrs/week | D21: Hours | E21: Note
A22: Version 1 — first build (name/dates: edit) | B22: 3 | C22: 3 | D22: =B22*C22*52 -> 468 | E22: guess — edit
A23: Version 2 — second build (name/dates: edit) | B23: 2 | C23: 4 | D23: =B23*C23*52 -> 416 | E23: guess — edit
A24: Prior hours subtotal | D24: =SUM(D22:D23) -> 884
A25: Rate for prior work, $/hr | B25: 175 | E25: same market rate as current work
A26: Carry-forward factor | B26: 0.35 | E26: share of the old work still serving today: brand, audience, content, lessons. Edit 0–1
A27: Prior versions value | B27: =D24*B25*B26 -> 54145
A28: GRAND TOTAL sweat equity (2026 work + prior carry-forward) | B28: =B13+B27 -> 92907.5
A29: Second lens: replacement cost — what an agency would charge to rebuild what existed Jan 1, 2026 (a comparable community app: $50k–150k). In investor talk, use whichever lens is higher and name the method.

Sheet Inputs
A1: Shared unit prices & policy toggles (all verified 2026-08-28 unless noted)
A3: Dues, $/member/month | B3: 10 | C3: Product decision (seat = platform membership)
A4: Platform take on money moved | B4: 0.1 | C4: Product decision — we earn 10% of money in motion
A5: Card fee — percent | B5: 0.029 | C5: stripe.com/pricing (2.9% + 30¢)
A6: Card fee — fixed $/transaction | B6: 0.3 | C6: stripe.com/pricing
A7: Stripe Billing fee (subscriptions) | B7: 0.007 | C7: stripe.com/billing/pricing (0.7% of billing volume)
A8: Avg non-dues transaction, $ | B8: 75 | C8: Assumption: typical project backing / class fee
A9: Platform absorbs processing? (1=yes, 0=passed to payer) | B9: 0 | C9: DECIDED 2026-09-08: payer covers processing at checkout
A10: Emails per member per month | B10: 10 | C10: Assumption: digests + event/RSVP + community posts
A11: Email cost per 1,000 sent | B11: 0.7 | C11: resend.com/pricing ($35/mo covers 100k; SES is $0.10/1k if we switch)
A12: SMS verifications per signup/yr | B12: 3 | C12: Assumption: signup + periodic re-auth (Twilio Verify)
A13: Cost per SMS verification | B13: 0.0583 | C13: twilio.com/en-us/verify/pricing ($0.05 + $0.0083/segment, US)
A14: Convex — developer seats | B14: 1 | C14: convex.dev/pricing ($25/dev/mo Professional)
... A23: Community event subsidy, $/community/yr | B23: 200 | C23: Assumption: small stipend per community gathering

Sheet S
A1: S — Small — SD only, slow build
B2: Y1 (Nov 26–Oct 27) | C2: Y2 | D2: Y3
A3: DRIVERS (blue = edit me)
A4: Avg paying members | B4: 150 | C4: 400 | D4: 900
A5: Communities | B5: 3 | C5: 5 | D5: 8
A6: Other money moved, $/member/yr | B6: 60 | C6: 80 | D6: 100
A7: New signups / yr | B7: 300 | C7: 500 | D7: 1000
A8: PT community staff, hrs/wk | B8: 10 | C8: 10 | D8: 15
A9: FT community staff, headcount | B9: 0 | C9: 0 | D9: 0
A10: Founder comp, $/yr | B10: 0 | C10: 0 | D10: 24000
A12: REVENUE
A13: Dues GMV | B13: =B4*Inputs!$B$3*12 -> 18000 | C13: =C4*Inputs!$B$3*12 -> 48000 | D13: =D4*Inputs!$B$3*12 -> 108000
A14: Other GMV (funding, classes, sponsorships) | B14: =B4*B6 -> 9000 | C14: =C4*C6 -> 32000 | D14: =D4*D6 -> 90000
A15: Total money moved (GMV) | B15: =B13+B14 -> 27000 | C15: =C13+C14 -> 80000 | D15: =D13+D14 -> 198000
A16: Platform gross (take × GMV) | B16: =B15*Inputs!$B$4 -> 2700 | C16: =C15*Inputs!$B$4 -> 8000 | D16: =D15*Inputs!$B$4 -> 19800
A17: Processing absorbed (cards + billing) | B17: =Inputs!$B$9*((B13*(Inputs!$B$5+Inputs!$B$7))+(B4*12*Inputs!$B$6)+(B14*(Inputs!$B$5+Inputs!$B$7))+(B14/Inputs!$B$8*Inputs!$B$6)) -> 0 | C17: =Inputs!$B$9*((C13*(Inputs!$B$5+Inputs!$B$7))+(C4*12*Inputs!$B$6)+(C14*(Inputs!$B$5+Inputs!$B$7))+(C14/Inputs!$B$8*Inputs!$B$6)) -> 0 | D17: =Inputs!$B$9*((D13*(Inputs!$B$5+Inputs!$B$7))+(D4*12*Inputs!$B$6)+(D14*(Inputs!$B$5+Inputs!$B$7))+(D14/Inputs!$B$8*Inputs!$B$6)) -> 0
A18: NET PLATFORM REVENUE | B18: =B16-B17 -> 2700 | C18: =C16-C17 -> 8000 | D18: =D16-D17 -> 19800
A20: COSTS
A21: Video (LiveKit tier) | B21: 0 | C21: 600 | D21: 600
A22: Email | B22: =B4*Inputs!$B$10*12/1000*Inputs!$B$11 -> 12.6 | C22: =C4*Inputs!$B$10*12/1000*Inputs!$B$11 -> 33.6 | D22: =D4*Inputs!$B$10*12/1000*Inputs!$B$11 -> 75.6
A23: SMS verification | B23: =B7*Inputs!$B$12*Inputs!$B$13 -> 52.47 | C23: =C7*Inputs!$B$12*Inputs!$B$13 -> 87.45 | D23: =D7*Inputs!$B$12*Inputs!$B$13 -> 174.9
A24: Convex (backend) | B24: =Inputs!$B$14*Inputs!$B$15*12+Inputs!$B$16 -> 600 | C24: =Inputs!$B$14*Inputs!$B$15*12+Inputs!$B$16 -> 600 | D24: =Inputs!$B$14*Inputs!$B$15*12+Inputs!$B$16 -> 600
A25: Cloudflare + domains + tools | B25: =Inputs!$B$17*12 -> 360 | C25: =Inputs!$B$17*12 -> 360 | D25: =Inputs!$B$17*12 -> 360
A26: Community staff — part-time | B26: =B8*Inputs!$B$18*52 -> 14736.8 | C26: =C8*Inputs!$B$18*52 -> 14736.8 | D26: =D8*Inputs!$B$18*52 -> 22105.2
A27: Community staff — full-time (loaded) | B27: =B9*Inputs!$B$19*Inputs!$B$20 -> 0 | C27: =C9*Inputs!$B$19*Inputs!$B$20 -> 0 | D27: =D9*Inputs!$B$19*Inputs!$B$20 -> 0
A28: Founder comp | B28: =B10 -> 0 | C28: =C10 -> 0 | D28: =D10 -> 24000
A29: Launch / annual event | B29: =Inputs!$B$21 -> 12000 | C29: 0 | D29: 0
A30: Film / testimonial series | B30: =Inputs!$B$22 -> 10000 | C30: 0 | D30: 0
A31: Community event subsidies | B31: =B5*Inputs!$B$23 -> 600 | C31: =C5*Inputs!$B$23 -> 1000 | D31: =D5*Inputs!$B$23 -> 1600
A32: G&A (legal, accounting, insurance) | B32: 4000 | C32: 4000 | D32: 5000
A33: TOTAL COSTS | B33: =SUM(B21:B32) -> 42361.87 | C33: =SUM(C21:C32) -> 21417.85 | D33: =SUM(D21:D32) -> 54515.7
A35: EBITDA | B35: =B18-B33 -> -39661.87 | C35: =C18-C33 -> -13417.85 | D35: =D18-D33 -> -34715.7
A36: Cumulative cash need | B36: =B35 -> -39661.87 | C36: =B36+C35 -> -53079.72 | D36: =C36+D35 -> -87795.42
A38: Memo: net revenue per member/yr | B38: =IF(B4=0,0,B18/B4) -> 18 | C38: =IF(C4=0,0,C18/C4) -> 20 | D38: =IF(D4=0,0,D18/D4) -> 22

Sheet M
A1: M — Medium — 3 metros by Y3
B2: Y1 (Nov 26–Oct 27) | C2: Y2 | D2: Y3
A3: DRIVERS (blue = edit me)
A4: Avg paying members | B4: 400 | C4: 1500 | D4: 4500
A5: Communities | B5: 6 | C5: 12 | D5: 20
A6: Other money moved, $/member/yr | B6: 100 | C6: 140 | D6: 180
A7: New signups / yr | B7: 800 | C7: 2200 | D7: 5000
A8: PT community staff, hrs/wk | B8: 15 | C8: 10 | D8: 10
A9: FT community staff, headcount | B9: 0 | C9: 1 | D9: 2
A10: Founder comp, $/yr | B10: 0 | C10: 48000 | D10: 72000
A12: REVENUE
A13: Dues GMV | B13: =B4*Inputs!$B$3*12 -> 48000 | C13: =C4*Inputs!$B$3*12 -> 180000 | D13: =D4*Inputs!$B$3*12 -> 540000
A14: Other GMV (funding, classes, sponsorships) | B14: =B4*B6 -> 40000 | C14: =C4*C6 -> 210000 | D14: =D4*D6 -> 810000
A15: Total money moved (GMV) | B15: =B13+B14 -> 88000 | C15: =C13+C14 -> 390000 | D15: =D13+D14 -> 1350000
A16: Platform gross (take × GMV) | B16: =B15*Inputs!$B$4 -> 8800 | C16: =C15*Inputs!$B$4 -> 39000 | D16: =D15*Inputs!$B$4 -> 135000
A17: Processing absorbed (cards + billing) | B17: =Inputs!$B$9*((B13*(Inputs!$B$5+Inputs!$B$7))+(B4*12*Inputs!$B$6)+(B14*(Inputs!$B$5+Inputs!$B$7))+(B14/Inputs!$B$8*Inputs!$B$6)) -> 0 | C17: =Inputs!$B$9*((C13*(Inputs!$B$5+Inputs!$B$7))+(C4*12*Inputs!$B$6)+(C14*(Inputs!$B$5+Inputs!$B$7))+(C14/Inputs!$B$8*Inputs!$B$6)) -> 0 | D17: =Inputs!$B$9*((D13*(Inputs!$B$5+Inputs!$B$7))+(D4*12*Inputs!$B$6)+(D14*(Inputs!$B$5+Inputs!$B$7))+(D14/Inputs!$B$8*Inputs!$B$6)) -> 0
A18: NET PLATFORM REVENUE | B18: =B16-B17 -> 8800 | C18: =C16-C17 -> 39000 | D18: =D16-D17 -> 135000
A20: COSTS
A21: Video (LiveKit tier) | B21: 600 | C21: 600 | D21: 1800
A22: Email | B22: =B4*Inputs!$B$10*12/1000*Inputs!$B$11 -> 33.6 | C22: =C4*Inputs!$B$10*12/1000*Inputs!$B$11 -> 126 | D22: =D4*Inputs!$B$10*12/1000*Inputs!$B$11 -> 378
A23: SMS verification | B23: =B7*Inputs!$B$12*Inputs!$B$13 -> 139.92 | C23: =C7*Inputs!$B$12*Inputs!$B$13 -> 384.78 | D23: =D7*Inputs!$B$12*Inputs!$B$13 -> 874.5
A24: Convex (backend) | B24: =Inputs!$B$14*Inputs!$B$15*12+Inputs!$B$16 -> 600 | C24: =Inputs!$B$14*Inputs!$B$15*12+Inputs!$B$16 -> 600 | D24: =Inputs!$B$14*Inputs!$B$15*12+Inputs!$B$16 -> 600
A25: Cloudflare + domains + tools | B25: =Inputs!$B$17*12 -> 360 | C25: =Inputs!$B$17*12 -> 360 | D25: =Inputs!$B$17*12 -> 360
A26: Community staff — part-time | B26: =B8*Inputs!$B$18*52 -> 22105.2 | C26: =C8*Inputs!$B$18*52 -> 14736.8 | D26: =D8*Inputs!$B$18*52 -> 14736.8
A27: Community staff — full-time (loaded) | B27: =B9*Inputs!$B$19*Inputs!$B$20 -> 0 | C27: =C9*Inputs!$B$19*Inputs!$B$20 -> 82500 | D27: =D9*Inputs!$B$19*Inputs!$B$20 -> 165000
A28: Founder comp | B28: =B10 -> 0 | C28: =C10 -> 48000 | D28: =D10 -> 72000
A29: Launch / annual event | B29: =Inputs!$B$21 -> 12000 | C29: 6000 | D29: 6000
A30: Film / testimonial series | B30: =Inputs!$B$22 -> 10000 | C30: 5000 | D30: 5000
A31: Community event subsidies | B31: =B5*Inputs!$B$23 -> 1200 | C31: =C5*Inputs!$B$23 -> 2400 | D31: =D5*Inputs!$B$23 -> 4000
A32: G&A (legal, accounting, insurance) | B32: 5000 | C32: 8000 | D32: 12000
A33: TOTAL COSTS | B33: =SUM(B21:B32) -> 52038.72 | C33: =SUM(C21:C32) -> 168707.58 | D33: =SUM(D21:D32) -> 282749.3
A35: EBITDA | B35: =B18-B33 -> -43238.72 | C35: =C18-C33 -> -129707.58 | D35: =D18-D33 -> -147749.3
A36: Cumulative cash need | B36: =B35 -> -43238.72 | C36: =B36+C35 -> -172946.3 | D36: =C36+D35 -> -320695.6
A38: Memo: net revenue per member/yr | B38: =IF(B4=0,0,B18/B4) -> 22 | C38: =IF(C4=0,0,C18/C4) -> 26 | D38: =IF(D4=0,0,D18/D4) -> 30

Sheet L
A1: L — Large — national network
B2: Y1 (Nov 26–Oct 27) | C2: Y2 | D2: Y3
A3: DRIVERS (blue = edit me)
A4: Avg paying members | B4: 1000 | C4: 5000 | D4: 15000
A5: Communities | B5: 10 | C5: 25 | D5: 50
A6: Other money moved, $/member/yr | B6: 150 | C6: 220 | D6: 300
A7: New signups / yr | B7: 2000 | C7: 7000 | D7: 18000
A8: PT community staff, hrs/wk | B8: 20 | C8: 10 | D8: 20
A9: FT community staff, headcount | B9: 1 | C9: 2 | D9: 4
A10: Founder comp, $/yr | B10: 48000 | C10: 72000 | D10: 96000
A12: REVENUE
A13: Dues GMV | B13: =B4*Inputs!$B$3*12 -> 120000 | C13: =C4*Inputs!$B$3*12 -> 600000 | D13: =D4*Inputs!$B$3*12 -> 1800000
A14: Other GMV (funding, classes, sponsorships) | B14: =B4*B6 -> 150000 | C14: =C4*C6 -> 1100000 | D14: =D4*D6 -> 4500000
A15: Total money moved (GMV) | B15: =B13+B14 -> 270000 | C15: =C13+C14 -> 1700000 | D15: =D13+D14 -> 6300000
A16: Platform gross (take × GMV) | B16: =B15*Inputs!$B$4 -> 27000 | C16: =C15*Inputs!$B$4 -> 170000 | D16: =D15*Inputs!$B$4 -> 630000
A17: Processing absorbed (cards + billing) | B17: =Inputs!$B$9*((B13*(Inputs!$B$5+Inputs!$B$7))+(B4*12*Inputs!$B$6)+(B14*(Inputs!$B$5+Inputs!$B$7))+(B14/Inputs!$B$8*Inputs!$B$6)) -> 0 | C17: =Inputs!$B$9*((C13*(Inputs!$B$5+Inputs!$B$7))+(C4*12*Inputs!$B$6)+(C14*(Inputs!$B$5+Inputs!$B$7))+(C14/Inputs!$B$8*Inputs!$B$6)) -> 0 | D17: =Inputs!$B$9*((D13*(Inputs!$B$5+Inputs!$B$7))+(D4*12*Inputs!$B$6)+(D14*(Inputs!$B$5+Inputs!$B$7))+(D14/Inputs!$B$8*Inputs!$B$6)) -> 0
A18: NET PLATFORM REVENUE | B18: =B16-B17 -> 27000 | C18: =C16-C17 -> 170000 | D18: =D16-D17 -> 630000
A20: COSTS
A21: Video (LiveKit tier) | B21: 600 | C21: 6000 | D21: 6000
A22: Email | B22: =B4*Inputs!$B$10*12/1000*Inputs!$B$11 -> 84 | C22: =C4*Inputs!$B$10*12/1000*Inputs!$B$11 -> 420 | D22: =D4*Inputs!$B$10*12/1000*Inputs!$B$11 -> 1260
A23: SMS verification | B23: =B7*Inputs!$B$12*Inputs!$B$13 -> 349.8 | C23: =C7*Inputs!$B$12*Inputs!$B$13 -> 1224.3 | D23: =D7*Inputs!$B$12*Inputs!$B$13 -> 3148.2
A24: Convex (backend) | B24: =Inputs!$B$14*Inputs!$B$15*12+Inputs!$B$16 -> 600 | C24: =Inputs!$B$14*Inputs!$B$15*12+Inputs!$B$16 -> 600 | D24: =Inputs!$B$14*Inputs!$B$15*12+Inputs!$B$16 -> 600
A25: Cloudflare + domains + tools | B25: =Inputs!$B$17*12 -> 360 | C25: =Inputs!$B$17*12 -> 360 | D25: =Inputs!$B$17*12 -> 360
A26: Community staff — part-time | B26: =B8*Inputs!$B$18*52 -> 29473.6 | C26: =C8*Inputs!$B$18*52 -> 14736.8 | D26: =D8*Inputs!$B$18*52 -> 29473.6
A27: Community staff — full-time (loaded) | B27: =B9*Inputs!$B$19*Inputs!$B$20 -> 82500 | C27: =C9*Inputs!$B$19*Inputs!$B$20 -> 165000 | D27: =D9*Inputs!$B$19*Inputs!$B$20 -> 330000
A28: Founder comp | B28: =B10 -> 48000 | C28: =C10 -> 72000 | D28: =D10 -> 96000
A29: Launch / annual event | B29: =Inputs!$B$21 -> 12000 | C29: 12000 | D29: 12000
A30: Film / testimonial series | B30: =Inputs!$B$22 -> 10000 | C30: 10000 | D30: 10000
A31: Community event subsidies | B31: =B5*Inputs!$B$23 -> 2000 | C31: =C5*Inputs!$B$23 -> 5000 | D31: =D5*Inputs!$B$23 -> 10000
A32: G&A (legal, accounting, insurance) | B32: 8000 | C32: 15000 | D32: 25000
A33: TOTAL COSTS | B33: =SUM(B21:B32) -> 193967.4 | C33: =SUM(C21:C32) -> 302341.1 | D33: =SUM(D21:D32) -> 523841.8
A35: EBITDA | B35: =B18-B33 -> -166967.4 | C35: =C18-C33 -> -132341.1 | D35: =D18-D33 -> 106158.2
A36: Cumulative cash need | B36: =B35 -> -166967.4 | C36: =B36+C35 -> -299308.5 | D36: =C36+D35 -> -193150.3
A38: Memo: net revenue per member/yr | B38: =IF(B4=0,0,B18/B4) -> 27 | C38: =IF(C4=0,0,C18/C4) -> 34 | D38: =IF(D4=0,0,D18/D4) -> 42

Sheet Summary
A1: Side by side — Year 3 of each scenario
B2: S | C2: M | D2: L
A3: Avg paying members Y3 | B3: =S!D4 -> 900 | C3: =M!D4 -> 4500 | D3: =L!D4 -> 15000
A4: Total GMV Y3 | B4: =S!D15 -> 198000 | C4: =M!D15 -> 1350000 | D4: =L!D15 -> 6300000
A5: Net platform revenue Y3 | B5: =S!D18 -> 19800 | C5: =M!D18 -> 135000 | D5: =L!D18 -> 630000
A6: Total costs Y3 | B6: =S!D33 -> 54515.7 | C6: =M!D33 -> 282749.3 | D6: =L!D33 -> 523841.8
A7: EBITDA Y3 | B7: =S!D35 -> -34715.7 | C7: =M!D35 -> -147749.3 | D7: =L!D35 -> 106158.2
A8: Cumulative cash need through Y3 | B8: =S!D36 -> -87795.42 | C8: =M!D36 -> -320695.6 | D8: =L!D36 -> -193150.3
A10: Founder time already invested | B10: ='Sweat Equity'!B13 -> 38762.5
A12: Flip Inputs!B9 to 0 (payer covers processing) and watch EBITDA — that one policy decides breakeven.
