Workbook

Sheet Summary
A1: Bootstrapped pathway: $10k to start, no salaries until revenue clears the threshold, then a share of revenue to the founders
A2: Three marketing levels side by side. Change the yellow cells on Inputs; everything here recalculates. Month 1 = November 2026.
B4: Lean | C4: Moderate | D4: Push
A5: MARKETING INPUTS (from Inputs)
A6: Paid acquisition, $/month | B6: =Inputs!$B$37 -> 0 | C6: =Inputs!$C$37 -> 300 | D6: =Inputs!$D$37 -> 800
A7: Organic adds per month | B7: =Inputs!$B$36 -> 3 | C7: =Inputs!$C$36 -> 6 | D7: =Inputs!$D$36 -> 10
A8: Gatherings per month | B8: =Inputs!$B$39 -> 1 | C8: =Inputs!$C$39 -> 2 | D8: =Inputs!$D$39 -> 3
A9: Organization packs sold per month | B9: =Inputs!$B$44 -> 0.25 | C9: =Inputs!$C$44 -> 0.5 | D9: =Inputs!$D$44 -> 1
A10: November 6 budget | B10: =Inputs!$B$42 -> 1500 | C10: =Inputs!$C$42 -> 3000 | D10: =Inputs!$D$42 -> 6000
A12: RESULTS
A13: Year 1 revenue | B13: =SUM(Lean!C23:N23) -> 16272.409 | C13: =SUM(Moderate!C23:N23) -> 35050.31 | D13: =SUM(Push!C23:N23) -> 71784.426
A14: Year 2 revenue | B14: =SUM(Lean!O23:Z23) -> 27283.902 | C14: =SUM(Moderate!O23:Z23) -> 69450.359 | D14: =SUM(Push!O23:Z23) -> 151776.25
A15: Year 3 revenue | B15: =SUM(Lean!AA23:AL23) -> 39464.026 | C15: =SUM(Moderate!AA23:AL23) -> 101010.65 | D15: =SUM(Push!AA23:AL23) -> 221274.45
A16: Year 1 marketing spend | B16: =SUM(Lean!C36:N36) -> 3300 | C16: =SUM(Moderate!C36:N36) -> 11400 | D16: =SUM(Push!C36:N36) -> 27600
A17: Year 2 marketing spend | B17: =SUM(Lean!O36:Z36) -> 1800 | C17: =SUM(Moderate!O36:Z36) -> 8400 | D17: =SUM(Push!O36:Z36) -> 18600
A18: Year 3 marketing spend | B18: =SUM(Lean!AA36:AL36) -> 1800 | C18: =SUM(Moderate!AA36:AL36) -> 8400 | D18: =SUM(Push!AA36:AL36) -> 18600
A19: Year 1 marketing as a share of revenue | B19: =IF(SUM(Lean!C23:N23)=0,0,SUM(Lean!C36:N36)/SUM(Lean!C23:N23)) -> 0.20279726 | C19: =IF(SUM(Moderate!C23:N23)=0,0,SUM(Moderate!C36:N36)/SUM(Moderate!C23:N23)) -> 0.32524677 | D19: =IF(SUM(Push!C23:N23)=0,0,SUM(Push!C36:N36)/SUM(Push!C23:N23)) -> 0.38448451
A20: Year 2 marketing as a share of revenue | B20: =IF(SUM(Lean!O23:Z23)=0,0,SUM(Lean!O36:Z36)/SUM(Lean!O23:Z23)) -> 0.065972968 | C20: =IF(SUM(Moderate!O23:Z23)=0,0,SUM(Moderate!O36:Z36)/SUM(Moderate!O23:Z23)) -> 0.1209497 | D20: =IF(SUM(Push!O23:Z23)=0,0,SUM(Push!O36:Z36)/SUM(Push!O23:Z23)) -> 0.12254882
A21: Year 3 marketing as a share of revenue | B21: =IF(SUM(Lean!AA23:AL23)=0,0,SUM(Lean!AA36:AL36)/SUM(Lean!AA23:AL23)) -> 0.04561116 | C21: =IF(SUM(Moderate!AA23:AL23)=0,0,SUM(Moderate!AA36:AL36)/SUM(Moderate!AA23:AL23)) -> 0.083159546 | D21: =IF(SUM(Push!AA23:AL23)=0,0,SUM(Push!AA36:AL36)/SUM(Push!AA23:AL23)) -> 0.084058508
A22: Monthly revenue, month 12 | B22: =Lean!N23 -> 1356.3172 | C22: =Moderate!N23 -> 3536.9182 | D22: =Push!N23 -> 7778.3786
A23: Monthly revenue, month 24 | B23: =Lean!Z23 -> 2404.6502 | C23: =Moderate!Z23 -> 6360.9278 | D23: =Push!Z23 -> 14070.659
A24: Monthly revenue, month 36 | B24: =Lean!AL23 -> 3394.7112 | C24: =Moderate!AL23 -> 8845.7117 | D24: =Push!AL23 -> 19487.244
A25: Recurring monthly revenue, month 12 | B25: =Lean!N22 -> 606.31724 | C25: =Moderate!N22 -> 2036.9182 | D25: =Push!N22 -> 4778.3786
A26: Recurring monthly revenue, month 36 | B26: =Lean!AL22 -> 1144.7112 | C26: =Moderate!AL22 -> 4345.7117 | D26: =Push!AL22 -> 10487.244
A27: Paying individuals, month 36 | B27: =Lean!AL10 -> 73.277787 | C27: =Moderate!AL10 -> 330.15283 | D27: =Push!AL10 -> 820.64674
A28: Members incl. organization seats, month 36 | B28: =Lean!AL13 -> 343.27779 | C28: =Moderate!AL13 -> 870.15283 | D28: =Push!AL13 -> 1900.6467
A30: CASH
A31: Lowest cash balance | B31: =MIN(Lean!C43:AL43) -> 10373.398 | C31: =MIN(Moderate!C43:AL43) -> 9204.675 | D31: =MIN(Push!C43:AL43) -> 6335.0749
A32: Month of the lowest balance | B32: =MATCH(MIN(Lean!C43:AL43),Lean!C43:AL43,0) -> 1 | C32: =MATCH(MIN(Moderate!C43:AL43),Moderate!C43:AL43,0) -> 1 | D32: =MATCH(MIN(Push!C43:AL43),Push!C43:AL43,0) -> 3
A33: Months with cash below zero (the plan is broken if this is not 0) | B33: =COUNTIF(Lean!C43:AL43,"<0") -> 0 | C33: =COUNTIF(Moderate!C43:AL43,"<0") -> 0 | D33: =COUNTIF(Push!C43:AL43,"<0") -> 0
A34: Cash at month 36 | B34: =Lean!AL43 -> 59542.401 | C34: =Moderate!AL43 -> 106186.47 | D34: =Push!AL43 -> 227706.28
A35: First month operating cash flow is positive | B35: =IFERROR(MATCH(TRUE,INDEX(Lean!C39:AL39>0,0),0),"never") -> 1 | C35: =IFERROR(MATCH(TRUE,INDEX(Moderate!C39:AL39>0,0),0),"never") -> 2 | D35: =IFERROR(MATCH(TRUE,INDEX(Push!C39:AL39>0,0),0),"never") -> 2
A37: FOUNDERS
A38: First month founders are paid | B38: =IFERROR(MATCH(TRUE,INDEX(Lean!C40:AL40>0,0),0),"never") -> 29 | C38: =IFERROR(MATCH(TRUE,INDEX(Moderate!C40:AL40>0,0),0),"never") -> 5 | D38: =IFERROR(MATCH(TRUE,INDEX(Push!C40:AL40>0,0),0),"never") -> 2
A39: Per founder per month, month 12 | B39: =Lean!N41 -> 0 | C39: =Moderate!N41 -> 530.53774 | D39: =Push!N41 -> 1166.7568
A40: Per founder per month, month 24 | B40: =Lean!Z41 -> 0 | C40: =Moderate!Z41 -> 954.13917 | D40: =Push!Z41 -> 2110.5989
A41: Per founder per month, month 36 | B41: =Lean!AL41 -> 509.20668 | C41: =Moderate!AL41 -> 1326.8568 | D41: =Push!AL41 -> 2923.0865
A42: Cumulative draw per founder over 36 months | B42: =Lean!AL44 -> 3994.4767 | C42: =Moderate!AL44 -> 29237.515 | D42: =Push!AL44 -> 65875.677
A44: Reading it: the founders keep their day jobs; the company pays for itself from month one on the Lean level and the distribution is beer money until organization packs sell. Revenue per member and organic adds are the two inputs that matter; test both in the first 90 days.

Sheet Inputs
A1: Bootstrapped model inputs (yellow cells are the variables; blue = hardcoded input)
A2: Month 1 = November 2026. Three marketing levels run side by side on their own sheets; single-value inputs apply to all three.
A4: CASH AND FOUNDERS
A5: Starting cash (the founders' own money or one small check) | B5: 10000
A6: Founder distributions start when monthly revenue reaches | B6: 1000 | E6: no salaries before this
A7: Share of monthly revenue distributed to founders once past the threshold | B7: 0.3 | E7: split evenly between the founders; applied to total revenue in the month
A8: Threshold measured on: 1 = recurring revenue (seats, share of money moved, program fee), 2 = total revenue incl. sponsorships and pack prepayments | B8: 1 | E8: 1 keeps a one-off sponsorship from triggering pay
A9: Founders sharing the distribution | B9: 2
A11: REVENUE DRIVERS
A12: Paying individuals at month 1 | B12: 20 | E12: waitlist conversions at launch
A13: Individual seat price, $/month | B13: 10 | E13: today's price
A14: Monthly churn of paying individuals | B14: 0.03 | E14: 3% a month = about 30% a year
A15: Seats per organization pack | B15: 30
A16: Organization pack price per seat per year | B16: 100 | E16: a 17% discount to $10/month, paid up front; packs renew after 12 months
A17: Money moved per member per month (backings, tickets, classes), $ | B17: 12 | E17: the platform keeps the take rate below
A18: Platform share of money moved | B18: 0.1
A19: Program dollars administered per month (fellowships), $ | B19: 0 | E19: grant money the nonprofit partner runs through the platform; 0 until a grant lands
A20: Administration fee on program dollars | B20: 0.05
A21: November 6 sponsorships collected, $ (month 1) | B21: 2000
A22: Other sponsorships per year, $ (spread evenly from month 7) | B22: 0
A24: FIXED AND VARIABLE COSTS (no people)
A25: Hosting and tools, $/month | B25: 150 | E25: Vercel/Supabase/Stripe-class stack plus email and design tools
A26: Payment processing absorbed, % of money moved | B26: 0.032
A27: Bookkeeping software and insurance, $/month | B27: 125
A28: Formation (Delaware C-corp, registered agent, CA qualification), $ in month 1 | B28: 700
A29: Delaware franchise tax and annual report, $ each March (months 5, 17, 29) | B29: 450
A30: California minimum franchise tax, $ (months 13 and 25; year one waived) | B30: 800
A31: Year-end tax return, $ each March | B31: 800
A32: Contractors (design, QA, video), $/month | B32: 0 | E32: the founders do the work
A34: MARKETING (back-of-napkin; one column per level)
B35: Lean | C35: Moderate | D35: Push
A36: Organic new paying individuals per month (word of mouth, gatherings, partners) | B36: 3 | C36: 6 | D36: 10 | E36: the number to test in the first 90 days
A37: Paid acquisition, $/month (social ads, boosted posts, flyers) | B37: 0 | C37: 300 | D37: 800
A38: Cost per new paying individual from paid acquisition, $ | B38: 40 | C38: 35 | D38: 30 | E38: $10/month subscriptions in niche communities run $25 to $60 per paying convert
A39: Gatherings per month (venue, food, printing) | B39: 1 | C39: 2 | D39: 3
A40: Cost per gathering, $ | B40: 150 | C40: 150 | D40: 150
A41: Content and community tools, $/month | B41: 0 | C41: 100 | D41: 300 | E41: print, small productions, email tool tier
A42: November 6 kickoff budget, $ (month 1) | B42: 1500 | C42: 3000 | D42: 6000 | E42: bootstrapped: venue donated, volunteers
A43: Testimonial film series, $ (month 3) | B43: 0 | C43: 0 | D43: 3000
A44: Organization seat packs sold per month | B44: 0.25 | C44: 0.5 | D44: 1 | E44: 0.25 = one pack a quarter; each is one conversation with a church, school or organization

Sheet Lean
A1: Lean marketing level, monthly, months 1 to 36 (month 1 = November 2026)
A2: Month | C2: 1 | D2: 2 | E2: 3 | F2: 4 | G2: 5 | H2: 6 | I2: 7 | J2: 8 | K2: 9 | L2: 10 | M2: 11 | N2: 12 | O2: 13 | P2: 14 | Q2: 15 | R2: 16 | S2: 17 | T2: 18 | U2: 19 | V2: 20 | W2: 21 | X2: 22 | Y2: 23 | Z2: 24 | AA2: 25 | AB2: 26 | AC2: 27 | AD2: 28 | AE2: 29 | AF2: 30 | AG2: 31 | AH2: 32 | AI2: 33 | AJ2: 34 | AK2: 35 | AL2: 36
A3: Year | C3: 1 | D3: 1 | E3: 1 | F3: 1 | G3: 1 | H3: 1 | I3: 1 | J3: 1 | K3: 1 | L3: 1 | M3: 1 | N3: 1 | O3: 2 | P3: 2 | Q3: 2 | R3: 2 | S3: 2 | T3: 2 | U3: 2 | V3: 2 | W3: 2 | X3: 2 | Y3: 2 | Z3: 2 | AA3: 3 | AB3: 3 | AC3: 3 | AD3: 3 | AE3: 3 | AF3: 3 | AG3: 3 | AH3: 3 | AI3: 3 | AJ3: 3 | AK3: 3 | AL3: 3
A5: MEMBERS
A6: Paying individuals, start of month | C6: =Inputs!$B$12 -> 20 | D6: =C10 -> 22.4 | E6: =D10 -> 24.728 | F6: =E10 -> 26.98616 | G6: =F10 -> 29.176575 | H6: =G10 -> 31.301278 | I6: =H10 -> 33.36224 | J6: =I10 -> 35.361372 | K6: =J10 -> 37.300531 | ... AL6: =AK10 -> 72.451327
A7: Organic adds | C7: =Inputs!$B$36 -> 3 | D7: =Inputs!$B$36 -> 3 | E7: =Inputs!$B$36 -> 3 | F7: =Inputs!$B$36 -> 3 | G7: =Inputs!$B$36 -> 3 | H7: =Inputs!$B$36 -> 3 | I7: =Inputs!$B$36 -> 3 | J7: =Inputs!$B$36 -> 3 | ... AL7: =Inputs!$B$36 -> 3
A8: Paid adds (paid $ / cost per convert) | C8: =IF(Inputs!$B$38=0,0,Inputs!$B$37/Inputs!$B$38) -> 0 | D8: =IF(Inputs!$B$38=0,0,Inputs!$B$37/Inputs!$B$38) -> 0 | E8: =IF(Inputs!$B$38=0,0,Inputs!$B$37/Inputs!$B$38) -> 0 | F8: =IF(Inputs!$B$38=0,0,Inputs!$B$37/Inputs!$B$38) -> 0 | G8: =IF(Inputs!$B$38=0,0,Inputs!$B$37/Inputs!$B$38) -> 0 | H8: =IF(Inputs!$B$38=0,0,Inputs!$B$37/Inputs!$B$38) -> 0 | I8: =IF(Inputs!$B$38=0,0,Inputs!$B$37/Inputs!$B$38) -> 0 | J8: =IF(Inputs!$B$38=0,0,Inputs!$B$37/Inputs!$B$38) -> 0 | ... AL8: =IF(Inputs!$B$38=0,0,Inputs!$B$37/Inputs!$B$38) -> 0
A9: Churned | C9: =-C6*Inputs!$B$14 -> -0.6 | D9: =-D6*Inputs!$B$14 -> -0.672 | E9: =-E6*Inputs!$B$14 -> -0.74184 | F9: =-F6*Inputs!$B$14 -> -0.8095848 | G9: =-G6*Inputs!$B$14 -> -0.87529726 | H9: =-H6*Inputs!$B$14 -> -0.93903834 | I9: =-I6*Inputs!$B$14 -> -1.0008672 | J9: =-J6*Inputs!$B$14 -> -1.0608412 | ... AL9: =-AL6*Inputs!$B$14 -> -2.1735398
A10: Paying individuals, end of month | C10: =C6+C7+C8+C9 -> 22.4 | D10: =D6+D7+D8+D9 -> 24.728 | E10: =E6+E7+E8+E9 -> 26.98616 | F10: =F6+F7+F8+F9 -> 29.176575 | G10: =G6+G7+G8+G9 -> 31.301278 | H10: =H6+H7+H8+H9 -> 33.36224 | I10: =I6+I7+I8+I9 -> 35.361372 | J10: =J6+J7+J8+J9 -> 37.300531 | ... AL10: =AL6+AL7+AL8+AL9 -> 73.277787
A11: Organization packs sold, cumulative | C11: =Inputs!$B$44 -> 0.25 | D11: =C11+Inputs!$B$44 -> 0.5 | E11: =D11+Inputs!$B$44 -> 0.75 | F11: =E11+Inputs!$B$44 -> 1 | G11: =F11+Inputs!$B$44 -> 1.25 | H11: =G11+Inputs!$B$44 -> 1.5 | I11: =H11+Inputs!$B$44 -> 1.75 | J11: =I11+Inputs!$B$44 -> 2 | K11: =J11+Inputs!$B$44 -> 2.25 | ... AL11: =AK11+Inputs!$B$44 -> 9
A12: Organization seats active | C12: =C11*Inputs!$B$15 -> 7.5 | D12: =D11*Inputs!$B$15 -> 15 | E12: =E11*Inputs!$B$15 -> 22.5 | F12: =F11*Inputs!$B$15 -> 30 | G12: =G11*Inputs!$B$15 -> 37.5 | H12: =H11*Inputs!$B$15 -> 45 | I12: =I11*Inputs!$B$15 -> 52.5 | J12: =J11*Inputs!$B$15 -> 60 | ... AL12: =AL11*Inputs!$B$15 -> 270
A13: Members (individuals + organization seats) | C13: =C10+C12 -> 29.9 | D13: =D10+D12 -> 39.728 | E13: =E10+E12 -> 49.48616 | F13: =F10+F12 -> 59.176575 | G13: =G10+G12 -> 68.801278 | H13: =H10+H12 -> 78.36224 | I13: =I10+I12 -> 87.861372 | J13: =J10+J12 -> 97.300531 | ... AL13: =AL10+AL12 -> 343.27779
A15: REVENUE
A16: Individual seats | C16: =C10*Inputs!$B$13 -> 224 | D16: =D10*Inputs!$B$13 -> 247.28 | E16: =E10*Inputs!$B$13 -> 269.8616 | F16: =F10*Inputs!$B$13 -> 291.76575 | G16: =G10*Inputs!$B$13 -> 313.01278 | H16: =H10*Inputs!$B$13 -> 333.6224 | I16: =I10*Inputs!$B$13 -> 353.61372 | J16: =J10*Inputs!$B$13 -> 373.00531 | ... AL16: =AL10*Inputs!$B$13 -> 732.77787
A17: Organization packs (cash at sale, renewals every 12 months) | C17: =Inputs!$B$44*Inputs!$B$15*Inputs!$B$16*1 -> 750 | D17: =Inputs!$B$44*Inputs!$B$15*Inputs!$B$16*1 -> 750 | E17: =Inputs!$B$44*Inputs!$B$15*Inputs!$B$16*1 -> 750 | F17: =Inputs!$B$44*Inputs!$B$15*Inputs!$B$16*1 -> 750 | G17: =Inputs!$B$44*Inputs!$B$15*Inputs!$B$16*1 -> 750 | H17: =Inputs!$B$44*Inputs!$B$15*Inputs!$B$16*1 -> 750 | I17: =Inputs!$B$44*Inputs!$B$15*Inputs!$B$16*1 -> 750 | J17: =Inputs!$B$44*Inputs!$B$15*Inputs!$B$16*1 -> 750 | ... N17: =Inputs!$B$44*Inputs!$B$15*Inputs!$B$16*1 -> 750 | O17: =Inputs!$B$44*Inputs!$B$15*Inputs!$B$16*2 -> 1500 | P17: =Inputs!$B$44*Inputs!$B$15*Inputs!$B$16*2 -> 1500 | Q17: =Inputs!$B$44*Inputs!$B$15*Inputs!$B$16*2 -> 1500 | R17: =Inputs!$B$44*Inputs!$B$15*Inputs!$B$16*2 -> 1500 | S17: =Inputs!$B$44*Inputs!$B$15*Inputs!$B$16*2 -> 1500 | T17: =Inputs!$B$44*Inputs!$B$15*Inputs!$B$16*2 -> 1500 | U17: =Inputs!$B$44*Inputs!$B$15*Inputs!$B$16*2 -> 1500 | V17: =Inputs!$B$44*Inputs!$B$15*Inputs!$B$16*2 -> 1500 | ... Z17: =Inputs!$B$44*Inputs!$B$15*Inputs!$B$16*2 -> 1500 | AA17: =Inputs!$B$44*Inputs!$B$15*Inputs!$B$16*3 -> 2250 | AB17: =Inputs!$B$44*Inputs!$B$15*Inputs!$B$16*3 -> 2250 | AC17: =Inputs!$B$44*Inputs!$B$15*Inputs!$B$16*3 -> 2250 | AD17: =Inputs!$B$44*Inputs!$B$15*Inputs!$B$16*3 -> 2250 | AE17: =Inputs!$B$44*Inputs!$B$15*Inputs!$B$16*3 -> 2250 | AF17: =Inputs!$B$44*Inputs!$B$15*Inputs!$B$16*3 -> 2250 | AG17: =Inputs!$B$44*Inputs!$B$15*Inputs!$B$16*3 -> 2250 | AH17: =Inputs!$B$44*Inputs!$B$15*Inputs!$B$16*3 -> 2250 | ... AL17: =Inputs!$B$44*Inputs!$B$15*Inputs!$B$16*3 -> 2250
A18: Money moved (memo) | C18: =C13*Inputs!$B$17 -> 358.8 | D18: =D13*Inputs!$B$17 -> 476.736 | E18: =E13*Inputs!$B$17 -> 593.83392 | F18: =F13*Inputs!$B$17 -> 710.1189 | G18: =G13*Inputs!$B$17 -> 825.61534 | H18: =H13*Inputs!$B$17 -> 940.34688 | I18: =I13*Inputs!$B$17 -> 1054.3365 | J18: =J13*Inputs!$B$17 -> 1167.6064 | ... AL18: =AL13*Inputs!$B$17 -> 4119.3334
A19: Platform share of money moved | C19: =C18*Inputs!$B$18 -> 35.88 | D19: =D18*Inputs!$B$18 -> 47.6736 | E19: =E18*Inputs!$B$18 -> 59.383392 | F19: =F18*Inputs!$B$18 -> 71.01189 | G19: =G18*Inputs!$B$18 -> 82.561534 | H19: =H18*Inputs!$B$18 -> 94.034688 | I19: =I18*Inputs!$B$18 -> 105.43365 | J19: =J18*Inputs!$B$18 -> 116.76064 | ... AL19: =AL18*Inputs!$B$18 -> 411.93334
A20: Program administration fee | C20: =Inputs!$B$19*Inputs!$B$20 -> 0 | D20: =Inputs!$B$19*Inputs!$B$20 -> 0 | E20: =Inputs!$B$19*Inputs!$B$20 -> 0 | F20: =Inputs!$B$19*Inputs!$B$20 -> 0 | G20: =Inputs!$B$19*Inputs!$B$20 -> 0 | H20: =Inputs!$B$19*Inputs!$B$20 -> 0 | I20: =Inputs!$B$19*Inputs!$B$20 -> 0 | J20: =Inputs!$B$19*Inputs!$B$20 -> 0 | ... AL20: =Inputs!$B$19*Inputs!$B$20 -> 0
A21: Sponsorships | C21: =Inputs!$B$21 -> 2000 | D21: =0 -> 0 | E21: =0 -> 0 | F21: =0 -> 0 | G21: =0 -> 0 | H21: =0 -> 0 | I21: =Inputs!$B$22/12 -> 0 | J21: =Inputs!$B$22/12 -> 0 | K21: =Inputs!$B$22/12 -> 0 | L21: =Inputs!$B$22/12 -> 0 | M21: =Inputs!$B$22/12 -> 0 | N21: =Inputs!$B$22/12 -> 0 | O21: =Inputs!$B$22/12 -> 0 | P21: =Inputs!$B$22/12 -> 0 | ... AL21: =Inputs!$B$22/12 -> 0
A22: Recurring revenue (memo: seats + share of money moved + program fee) | C22: =C16+C19+C20 -> 259.88 | D22: =D16+D19+D20 -> 294.9536 | E22: =E16+E19+E20 -> 329.24499 | F22: =F16+F19+F20 -> 362.77764 | G22: =G16+G19+G20 -> 395.57431 | H22: =H16+H19+H20 -> 427.65708 | I22: =I16+I19+I20 -> 459.04737 | J22: =J16+J19+J20 -> 489.76595 | ... AL22: =AL16+AL19+AL20 -> 1144.7112
A23: TOTAL REVENUE | C23: =C16+C17+C19+C20+C21 -> 3009.88 | D23: =D16+D17+D19+D20+D21 -> 1044.9536 | E23: =E16+E17+E19+E20+E21 -> 1079.245 | F23: =F16+F17+F19+F20+F21 -> 1112.7776 | G23: =G16+G17+G19+G20+G21 -> 1145.5743 | H23: =H16+H17+H19+H20+H21 -> 1177.6571 | I23: =I16+I17+I19+I20+I21 -> 1209.0474 | J23: =J16+J17+J19+J20+J21 -> 1239.7659 | ... AL23: =AL16+AL17+AL19+AL20+AL21 -> 3394.7112
A25: COSTS BEFORE FOUNDERS
A26: Hosting and tools | C26: =Inputs!$B$25 -> 150 | D26: =Inputs!$B$25 -> 150 | E26: =Inputs!$B$25 -> 150 | F26: =Inputs!$B$25 -> 150 | G26: =Inputs!$B$25 -> 150 | H26: =Inputs!$B$25 -> 150 | I26: =Inputs!$B$25 -> 150 | J26: =Inputs!$B$25 -> 150 | ... AL26: =Inputs!$B$25 -> 150
A27: Payment processing | C27: =C18*Inputs!$B$26 -> 11.4816 | D27: =D18*Inputs!$B$26 -> 15.255552 | E27: =E18*Inputs!$B$26 -> 19.002685 | F27: =F18*Inputs!$B$26 -> 22.723805 | G27: =G18*Inputs!$B$26 -> 26.419691 | H27: =H18*Inputs!$B$26 -> 30.0911 | I27: =I18*Inputs!$B$26 -> 33.738767 | J27: =J18*Inputs!$B$26 -> 37.363404 | ... AL27: =AL18*Inputs!$B$26 -> 131.81867
A28: Bookkeeping and insurance | C28: =Inputs!$B$27 -> 125 | D28: =Inputs!$B$27 -> 125 | E28: =Inputs!$B$27 -> 125 | F28: =Inputs!$B$27 -> 125 | G28: =Inputs!$B$27 -> 125 | H28: =Inputs!$B$27 -> 125 | I28: =Inputs!$B$27 -> 125 | J28: =Inputs!$B$27 -> 125 | ... AL28: =Inputs!$B$27 -> 125
A29: Formation, franchise taxes, tax return | C29: =Inputs!$B$28 -> 700 | D29: =0 -> 0 | E29: =0 -> 0 | F29: =0 -> 0 | G29: =Inputs!$B$29+Inputs!$B$31 -> 1250 | H29: =0 -> 0 | I29: =0 -> 0 | J29: =0 -> 0 | K29: =0 -> 0 | L29: =0 -> 0 | M29: =0 -> 0 | N29: =0 -> 0 | O29: =Inputs!$B$30 -> 800 | P29: =0 -> 0 | Q29: =0 -> 0 | R29: =0 -> 0 | S29: =Inputs!$B$29+Inputs!$B$31 -> 1250 | T29: =0 -> 0 | U29: =0 -> 0 | V29: =0 -> 0 | W29: =0 -> 0 | X29: =0 -> 0 | Y29: =0 -> 0 | Z29: =0 -> 0 | AA29: =Inputs!$B$30 -> 800 | AB29: =0 -> 0 | AC29: =0 -> 0 | AD29: =0 -> 0 | AE29: =Inputs!$B$29+Inputs!$B$31 -> 1250 | AF29: =0 -> 0 | AG29: =0 -> 0 | AH29: =0 -> 0 | AI29: =0 -> 0 | AJ29: =0 -> 0 | AK29: =0 -> 0 | AL29: =0 -> 0
A30: Contractors | C30: =Inputs!$B$32 -> 0 | D30: =Inputs!$B$32 -> 0 | E30: =Inputs!$B$32 -> 0 | F30: =Inputs!$B$32 -> 0 | G30: =Inputs!$B$32 -> 0 | H30: =Inputs!$B$32 -> 0 | I30: =Inputs!$B$32 -> 0 | J30: =Inputs!$B$32 -> 0 | ... AL30: =Inputs!$B$32 -> 0
A31: Marketing: paid acquisition | C31: =Inputs!$B$37 -> 0 | D31: =Inputs!$B$37 -> 0 | E31: =Inputs!$B$37 -> 0 | F31: =Inputs!$B$37 -> 0 | G31: =Inputs!$B$37 -> 0 | H31: =Inputs!$B$37 -> 0 | I31: =Inputs!$B$37 -> 0 | J31: =Inputs!$B$37 -> 0 | ... AL31: =Inputs!$B$37 -> 0
A32: Marketing: gatherings | C32: =Inputs!$B$39*Inputs!$B$40 -> 150 | D32: =Inputs!$B$39*Inputs!$B$40 -> 150 | E32: =Inputs!$B$39*Inputs!$B$40 -> 150 | F32: =Inputs!$B$39*Inputs!$B$40 -> 150 | G32: =Inputs!$B$39*Inputs!$B$40 -> 150 | H32: =Inputs!$B$39*Inputs!$B$40 -> 150 | I32: =Inputs!$B$39*Inputs!$B$40 -> 150 | J32: =Inputs!$B$39*Inputs!$B$40 -> 150 | ... AL32: =Inputs!$B$39*Inputs!$B$40 -> 150
A33: Marketing: content and tools | C33: =Inputs!$B$41 -> 0 | D33: =Inputs!$B$41 -> 0 | E33: =Inputs!$B$41 -> 0 | F33: =Inputs!$B$41 -> 0 | G33: =Inputs!$B$41 -> 0 | H33: =Inputs!$B$41 -> 0 | I33: =Inputs!$B$41 -> 0 | J33: =Inputs!$B$41 -> 0 | ... AL33: =Inputs!$B$41 -> 0
A34: Marketing: November 6 and the film series | C34: =Inputs!$B$42 -> 1500 | D34: =0 -> 0 | E34: =Inputs!$B$43 -> 0 | F34: =0 -> 0 | G34: =0 -> 0 | H34: =0 -> 0 | I34: =0 -> 0 | J34: =0 -> 0 | K34: =0 -> 0 | L34: =0 -> 0 | M34: =0 -> 0 | ... AL34: =0 -> 0
A35: TOTAL COSTS BEFORE FOUNDERS | C35: =SUM(C26:C34) -> 2636.4816 | D35: =SUM(D26:D34) -> 440.25555 | E35: =SUM(E26:E34) -> 444.00269 | F35: =SUM(F26:F34) -> 447.7238 | G35: =SUM(G26:G34) -> 1701.4197 | H35: =SUM(H26:H34) -> 455.0911 | I35: =SUM(I26:I34) -> 458.73877 | J35: =SUM(J26:J34) -> 462.3634 | ... AL35: =SUM(AL26:AL34) -> 556.81867
A36: of which marketing | C36: =SUM(C31:C34) -> 1650 | D36: =SUM(D31:D34) -> 150 | E36: =SUM(E31:E34) -> 150 | F36: =SUM(F31:F34) -> 150 | G36: =SUM(G31:G34) -> 150 | H36: =SUM(H31:H34) -> 150 | I36: =SUM(I31:I34) -> 150 | J36: =SUM(J31:J34) -> 150 | ... AL36: =SUM(AL31:AL34) -> 150
A38: CASH
A39: Operating cash flow (revenue less costs) | C39: =C23-C35 -> 373.3984 | D39: =D23-D35 -> 604.69805 | E39: =E23-E35 -> 635.24231 | F39: =F23-F35 -> 665.05384 | G39: =G23-G35 -> -555.84538 | H39: =H23-H35 -> 722.56598 | I39: =I23-I35 -> 750.3086 | J39: =J23-J35 -> 777.40255 | ... AL39: =AL23-AL35 -> 2837.8925
A40: Founder distributions (share of revenue once past the threshold) | C40: =IF(IF(Inputs!$B$8=1,C22,C23)>=Inputs!$B$6,C23*Inputs!$B$7,0) -> 0 | D40: =IF(IF(Inputs!$B$8=1,D22,D23)>=Inputs!$B$6,D23*Inputs!$B$7,0) -> 0 | E40: =IF(IF(Inputs!$B$8=1,E22,E23)>=Inputs!$B$6,E23*Inputs!$B$7,0) -> 0 | F40: =IF(IF(Inputs!$B$8=1,F22,F23)>=Inputs!$B$6,F23*Inputs!$B$7,0) -> 0 | G40: =IF(IF(Inputs!$B$8=1,G22,G23)>=Inputs!$B$6,G23*Inputs!$B$7,0) -> 0 | H40: =IF(IF(Inputs!$B$8=1,H22,H23)>=Inputs!$B$6,H23*Inputs!$B$7,0) -> 0 | I40: =IF(IF(Inputs!$B$8=1,I22,I23)>=Inputs!$B$6,I23*Inputs!$B$7,0) -> 0 | J40: =IF(IF(Inputs!$B$8=1,J22,J23)>=Inputs!$B$6,J23*Inputs!$B$7,0) -> 0 | ... AL40: =IF(IF(Inputs!$B$8=1,AL22,AL23)>=Inputs!$B$6,AL23*Inputs!$B$7,0) -> 1018.4134
A41: per founder | C41: =C40/Inputs!$B$9 -> 0 | D41: =D40/Inputs!$B$9 -> 0 | E41: =E40/Inputs!$B$9 -> 0 | F41: =F40/Inputs!$B$9 -> 0 | G41: =G40/Inputs!$B$9 -> 0 | H41: =H40/Inputs!$B$9 -> 0 | I41: =I40/Inputs!$B$9 -> 0 | J41: =J40/Inputs!$B$9 -> 0 | ... AL41: =AL40/Inputs!$B$9 -> 509.20668
A42: Net cash flow | C42: =C39-C40 -> 373.3984 | D42: =D39-D40 -> 604.69805 | E42: =E39-E40 -> 635.24231 | F42: =F39-F40 -> 665.05384 | G42: =G39-G40 -> -555.84538 | H42: =H39-H40 -> 722.56598 | I42: =I39-I40 -> 750.3086 | J42: =J39-J40 -> 777.40255 | ... AL42: =AL39-AL40 -> 1819.4792
A43: CASH, END OF MONTH | C43: =Inputs!$B$5+C42 -> 10373.398 | D43: =C43+D42 -> 10978.096 | E43: =D43+E42 -> 11613.339 | F43: =E43+F42 -> 12278.393 | G43: =F43+G42 -> 11722.547 | H43: =G43+H42 -> 12445.113 | I43: =H43+I42 -> 13195.422 | J43: =I43+J42 -> 13972.824 | K43: =J43+K42 -> 14776.692 | ... AL43: =AK43+AL42 -> 59542.401
A44: Cumulative founder draw, each | C44: =C41 -> 0 | D44: =C44+D41 -> 0 | E44: =D44+E41 -> 0 | F44: =E44+F41 -> 0 | G44: =F44+G41 -> 0 | H44: =G44+H41 -> 0 | I44: =H44+I41 -> 0 | J44: =I44+J41 -> 0 | K44: =J44+K41 -> 0 | ... AL44: =AK44+AL41 -> 3994.4767

Sheet Moderate
A1: Moderate marketing level, monthly, months 1 to 36 (month 1 = November 2026)
A2: Month | C2: 1 | D2: 2 | E2: 3 | F2: 4 | G2: 5 | H2: 6 | I2: 7 | J2: 8 | K2: 9 | L2: 10 | M2: 11 | N2: 12 | O2: 13 | P2: 14 | Q2: 15 | R2: 16 | S2: 17 | T2: 18 | U2: 19 | V2: 20 | W2: 21 | X2: 22 | Y2: 23 | Z2: 24 | AA2: 25 | AB2: 26 | AC2: 27 | AD2: 28 | AE2: 29 | AF2: 30 | AG2: 31 | AH2: 32 | AI2: 33 | AJ2: 34 | AK2: 35 | AL2: 36
A3: Year | C3: 1 | D3: 1 | E3: 1 | F3: 1 | G3: 1 | H3: 1 | I3: 1 | J3: 1 | K3: 1 | L3: 1 | M3: 1 | N3: 1 | O3: 2 | P3: 2 | Q3: 2 | R3: 2 | S3: 2 | T3: 2 | U3: 2 | V3: 2 | W3: 2 | X3: 2 | Y3: 2 | Z3: 2 | AA3: 3 | AB3: 3 | AC3: 3 | AD3: 3 | AE3: 3 | AF3: 3 | AG3: 3 | AH3: 3 | AI3: 3 | AJ3: 3 | AK3: 3 | AL3: 3
A5: MEMBERS
A6: Paying individuals, start of month | C6: =Inputs!$B$12 -> 20 | D6: =C10 -> 33.971429 | E6: =D10 -> 47.523714 | F6: =E10 -> 60.669431 | G6: =F10 -> 73.420777 | H6: =G10 -> 85.789582 | I6: =H10 -> 97.787323 | J6: =I10 -> 109.42513 | K6: =J10 -> 120.71381 | ... AL6: =AK10 -> 325.34165
A7: Organic adds | C7: =Inputs!$C$36 -> 6 | D7: =Inputs!$C$36 -> 6 | E7: =Inputs!$C$36 -> 6 | F7: =Inputs!$C$36 -> 6 | G7: =Inputs!$C$36 -> 6 | H7: =Inputs!$C$36 -> 6 | I7: =Inputs!$C$36 -> 6 | J7: =Inputs!$C$36 -> 6 | ... AL7: =Inputs!$C$36 -> 6
A8: Paid adds (paid $ / cost per convert) | C8: =IF(Inputs!$C$38=0,0,Inputs!$C$37/Inputs!$C$38) -> 8.5714286 | D8: =IF(Inputs!$C$38=0,0,Inputs!$C$37/Inputs!$C$38) -> 8.5714286 | E8: =IF(Inputs!$C$38=0,0,Inputs!$C$37/Inputs!$C$38) -> 8.5714286 | F8: =IF(Inputs!$C$38=0,0,Inputs!$C$37/Inputs!$C$38) -> 8.5714286 | G8: =IF(Inputs!$C$38=0,0,Inputs!$C$37/Inputs!$C$38) -> 8.5714286 | H8: =IF(Inputs!$C$38=0,0,Inputs!$C$37/Inputs!$C$38) -> 8.5714286 | I8: =IF(Inputs!$C$38=0,0,Inputs!$C$37/Inputs!$C$38) -> 8.5714286 | J8: =IF(Inputs!$C$38=0,0,Inputs!$C$37/Inputs!$C$38) -> 8.5714286 | ... AL8: =IF(Inputs!$C$38=0,0,Inputs!$C$37/Inputs!$C$38) -> 8.5714286
A9: Churned | C9: =-C6*Inputs!$B$14 -> -0.6 | D9: =-D6*Inputs!$B$14 -> -1.0191429 | E9: =-E6*Inputs!$B$14 -> -1.4257114 | F9: =-F6*Inputs!$B$14 -> -1.8200829 | G9: =-G6*Inputs!$B$14 -> -2.2026233 | H9: =-H6*Inputs!$B$14 -> -2.5736875 | I9: =-I6*Inputs!$B$14 -> -2.9336197 | J9: =-J6*Inputs!$B$14 -> -3.282754 | ... AL9: =-AL6*Inputs!$B$14 -> -9.7602496
A10: Paying individuals, end of month | C10: =C6+C7+C8+C9 -> 33.971429 | D10: =D6+D7+D8+D9 -> 47.523714 | E10: =E6+E7+E8+E9 -> 60.669431 | F10: =F6+F7+F8+F9 -> 73.420777 | G10: =G6+G7+G8+G9 -> 85.789582 | H10: =H6+H7+H8+H9 -> 97.787323 | I10: =I6+I7+I8+I9 -> 109.42513 | J10: =J6+J7+J8+J9 -> 120.71381 | ... AL10: =AL6+AL7+AL8+AL9 -> 330.15283
A11: Organization packs sold, cumulative | C11: =Inputs!$C$44 -> 0.5 | D11: =C11+Inputs!$C$44 -> 1 | E11: =D11+Inputs!$C$44 -> 1.5 | F11: =E11+Inputs!$C$44 -> 2 | G11: =F11+Inputs!$C$44 -> 2.5 | H11: =G11+Inputs!$C$44 -> 3 | I11: =H11+Inputs!$C$44 -> 3.5 | J11: =I11+Inputs!$C$44 -> 4 | K11: =J11+Inputs!$C$44 -> 4.5 | ... AL11: =AK11+Inputs!$C$44 -> 18
A12: Organization seats active | C12: =C11*Inputs!$B$15 -> 15 | D12: =D11*Inputs!$B$15 -> 30 | E12: =E11*Inputs!$B$15 -> 45 | F12: =F11*Inputs!$B$15 -> 60 | G12: =G11*Inputs!$B$15 -> 75 | H12: =H11*Inputs!$B$15 -> 90 | I12: =I11*Inputs!$B$15 -> 105 | J12: =J11*Inputs!$B$15 -> 120 | ... AL12: =AL11*Inputs!$B$15 -> 540
A13: Members (individuals + organization seats) | C13: =C10+C12 -> 48.971429 | D13: =D10+D12 -> 77.523714 | E13: =E10+E12 -> 105.66943 | F13: =F10+F12 -> 133.42078 | G13: =G10+G12 -> 160.78958 | H13: =H10+H12 -> 187.78732 | I13: =I10+I12 -> 214.42513 | J13: =J10+J12 -> 240.71381 | ... AL13: =AL10+AL12 -> 870.15283
A15: REVENUE
A16: Individual seats | C16: =C10*Inputs!$B$13 -> 339.71429 | D16: =D10*Inputs!$B$13 -> 475.23714 | E16: =E10*Inputs!$B$13 -> 606.69431 | F16: =F10*Inputs!$B$13 -> 734.20777 | G16: =G10*Inputs!$B$13 -> 857.89582 | H16: =H10*Inputs!$B$13 -> 977.87323 | I16: =I10*Inputs!$B$13 -> 1094.2513 | J16: =J10*Inputs!$B$13 -> 1207.1381 | ... AL16: =AL10*Inputs!$B$13 -> 3301.5283
A17: Organization packs (cash at sale, renewals every 12 months) | C17: =Inputs!$C$44*Inputs!$B$15*Inputs!$B$16*1 -> 1500 | D17: =Inputs!$C$44*Inputs!$B$15*Inputs!$B$16*1 -> 1500 | E17: =Inputs!$C$44*Inputs!$B$15*Inputs!$B$16*1 -> 1500 | F17: =Inputs!$C$44*Inputs!$B$15*Inputs!$B$16*1 -> 1500 | G17: =Inputs!$C$44*Inputs!$B$15*Inputs!$B$16*1 -> 1500 | H17: =Inputs!$C$44*Inputs!$B$15*Inputs!$B$16*1 -> 1500 | I17: =Inputs!$C$44*Inputs!$B$15*Inputs!$B$16*1 -> 1500 | J17: =Inputs!$C$44*Inputs!$B$15*Inputs!$B$16*1 -> 1500 | ... N17: =Inputs!$C$44*Inputs!$B$15*Inputs!$B$16*1 -> 1500 | O17: =Inputs!$C$44*Inputs!$B$15*Inputs!$B$16*2 -> 3000 | P17: =Inputs!$C$44*Inputs!$B$15*Inputs!$B$16*2 -> 3000 | Q17: =Inputs!$C$44*Inputs!$B$15*Inputs!$B$16*2 -> 3000 | R17: =Inputs!$C$44*Inputs!$B$15*Inputs!$B$16*2 -> 3000 | S17: =Inputs!$C$44*Inputs!$B$15*Inputs!$B$16*2 -> 3000 | T17: =Inputs!$C$44*Inputs!$B$15*Inputs!$B$16*2 -> 3000 | U17: =Inputs!$C$44*Inputs!$B$15*Inputs!$B$16*2 -> 3000 | V17: =Inputs!$C$44*Inputs!$B$15*Inputs!$B$16*2 -> 3000 | ... Z17: =Inputs!$C$44*Inputs!$B$15*Inputs!$B$16*2 -> 3000 | AA17: =Inputs!$C$44*Inputs!$B$15*Inputs!$B$16*3 -> 4500 | AB17: =Inputs!$C$44*Inputs!$B$15*Inputs!$B$16*3 -> 4500 | AC17: =Inputs!$C$44*Inputs!$B$15*Inputs!$B$16*3 -> 4500 | AD17: =Inputs!$C$44*Inputs!$B$15*Inputs!$B$16*3 -> 4500 | AE17: =Inputs!$C$44*Inputs!$B$15*Inputs!$B$16*3 -> 4500 | AF17: =Inputs!$C$44*Inputs!$B$15*Inputs!$B$16*3 -> 4500 | AG17: =Inputs!$C$44*Inputs!$B$15*Inputs!$B$16*3 -> 4500 | AH17: =Inputs!$C$44*Inputs!$B$15*Inputs!$B$16*3 -> 4500 | ... AL17: =Inputs!$C$44*Inputs!$B$15*Inputs!$B$16*3 -> 4500
A18: Money moved (memo) | C18: =C13*Inputs!$B$17 -> 587.65714 | D18: =D13*Inputs!$B$17 -> 930.28457 | E18: =E13*Inputs!$B$17 -> 1268.0332 | F18: =F13*Inputs!$B$17 -> 1601.0493 | G18: =G13*Inputs!$B$17 -> 1929.475 | H18: =H13*Inputs!$B$17 -> 2253.4479 | I18: =I13*Inputs!$B$17 -> 2573.1016 | J18: =J13*Inputs!$B$17 -> 2888.5657 | ... AL18: =AL13*Inputs!$B$17 -> 10441.834
A19: Platform share of money moved | C19: =C18*Inputs!$B$18 -> 58.765714 | D19: =D18*Inputs!$B$18 -> 93.028457 | E19: =E18*Inputs!$B$18 -> 126.80332 | F19: =F18*Inputs!$B$18 -> 160.10493 | G19: =G18*Inputs!$B$18 -> 192.9475 | H19: =H18*Inputs!$B$18 -> 225.34479 | I19: =I18*Inputs!$B$18 -> 257.31016 | J19: =J18*Inputs!$B$18 -> 288.85657 | ... AL19: =AL18*Inputs!$B$18 -> 1044.1834
A20: Program administration fee | C20: =Inputs!$B$19*Inputs!$B$20 -> 0 | D20: =Inputs!$B$19*Inputs!$B$20 -> 0 | E20: =Inputs!$B$19*Inputs!$B$20 -> 0 | F20: =Inputs!$B$19*Inputs!$B$20 -> 0 | G20: =Inputs!$B$19*Inputs!$B$20 -> 0 | H20: =Inputs!$B$19*Inputs!$B$20 -> 0 | I20: =Inputs!$B$19*Inputs!$B$20 -> 0 | J20: =Inputs!$B$19*Inputs!$B$20 -> 0 | ... AL20: =Inputs!$B$19*Inputs!$B$20 -> 0
A21: Sponsorships | C21: =Inputs!$B$21 -> 2000 | D21: =0 -> 0 | E21: =0 -> 0 | F21: =0 -> 0 | G21: =0 -> 0 | H21: =0 -> 0 | I21: =Inputs!$B$22/12 -> 0 | J21: =Inputs!$B$22/12 -> 0 | K21: =Inputs!$B$22/12 -> 0 | L21: =Inputs!$B$22/12 -> 0 | M21: =Inputs!$B$22/12 -> 0 | N21: =Inputs!$B$22/12 -> 0 | O21: =Inputs!$B$22/12 -> 0 | P21: =Inputs!$B$22/12 -> 0 | ... AL21: =Inputs!$B$22/12 -> 0
A22: Recurring revenue (memo: seats + share of money moved + program fee) | C22: =C16+C19+C20 -> 398.48 | D22: =D16+D19+D20 -> 568.2656 | E22: =E16+E19+E20 -> 733.49763 | F22: =F16+F19+F20 -> 894.3127 | G22: =G16+G19+G20 -> 1050.8433 | H22: =H16+H19+H20 -> 1203.218 | I22: =I16+I19+I20 -> 1351.5615 | J22: =J16+J19+J20 -> 1495.9946 | ... AL22: =AL16+AL19+AL20 -> 4345.7117
A23: TOTAL REVENUE | C23: =C16+C17+C19+C20+C21 -> 3898.48 | D23: =D16+D17+D19+D20+D21 -> 2068.2656 | E23: =E16+E17+E19+E20+E21 -> 2233.4976 | F23: =F16+F17+F19+F20+F21 -> 2394.3127 | G23: =G16+G17+G19+G20+G21 -> 2550.8433 | H23: =H16+H17+H19+H20+H21 -> 2703.218 | I23: =I16+I17+I19+I20+I21 -> 2851.5615 | J23: =J16+J17+J19+J20+J21 -> 2995.9946 | ... AL23: =AL16+AL17+AL19+AL20+AL21 -> 8845.7117
A25: COSTS BEFORE FOUNDERS
A26: Hosting and tools | C26: =Inputs!$B$25 -> 150 | D26: =Inputs!$B$25 -> 150 | E26: =Inputs!$B$25 -> 150 | F26: =Inputs!$B$25 -> 150 | G26: =Inputs!$B$25 -> 150 | H26: =Inputs!$B$25 -> 150 | I26: =Inputs!$B$25 -> 150 | J26: =Inputs!$B$25 -> 150 | ... AL26: =Inputs!$B$25 -> 150
A27: Payment processing | C27: =C18*Inputs!$B$26 -> 18.805029 | D27: =D18*Inputs!$B$26 -> 29.769106 | E27: =E18*Inputs!$B$26 -> 40.577062 | F27: =F18*Inputs!$B$26 -> 51.233578 | G27: =G18*Inputs!$B$26 -> 61.7432 | H27: =H18*Inputs!$B$26 -> 72.110332 | I27: =I18*Inputs!$B$26 -> 82.339251 | J27: =J18*Inputs!$B$26 -> 92.434102 | ... AL27: =AL18*Inputs!$B$26 -> 334.13869
A28: Bookkeeping and insurance | C28: =Inputs!$B$27 -> 125 | D28: =Inputs!$B$27 -> 125 | E28: =Inputs!$B$27 -> 125 | F28: =Inputs!$B$27 -> 125 | G28: =Inputs!$B$27 -> 125 | H28: =Inputs!$B$27 -> 125 | I28: =Inputs!$B$27 -> 125 | J28: =Inputs!$B$27 -> 125 | ... AL28: =Inputs!$B$27 -> 125
A29: Formation, franchise taxes, tax return | C29: =Inputs!$B$28 -> 700 | D29: =0 -> 0 | E29: =0 -> 0 | F29: =0 -> 0 | G29: =Inputs!$B$29+Inputs!$B$31 -> 1250 | H29: =0 -> 0 | I29: =0 -> 0 | J29: =0 -> 0 | K29: =0 -> 0 | L29: =0 -> 0 | M29: =0 -> 0 | N29: =0 -> 0 | O29: =Inputs!$B$30 -> 800 | P29: =0 -> 0 | Q29: =0 -> 0 | R29: =0 -> 0 | S29: =Inputs!$B$29+Inputs!$B$31 -> 1250 | T29: =0 -> 0 | U29: =0 -> 0 | V29: =0 -> 0 | W29: =0 -> 0 | X29: =0 -> 0 | Y29: =0 -> 0 | Z29: =0 -> 0 | AA29: =Inputs!$B$30 -> 800 | AB29: =0 -> 0 | AC29: =0 -> 0 | AD29: =0 -> 0 | AE29: =Inputs!$B$29+Inputs!$B$31 -> 1250 | AF29: =0 -> 0 | AG29: =0 -> 0 | AH29: =0 -> 0 | AI29: =0 -> 0 | AJ29: =0 -> 0 | AK29: =0 -> 0 | AL29: =0 -> 0
A30: Contractors | C30: =Inputs!$B$32 -> 0 | D30: =Inputs!$B$32 -> 0 | E30: =Inputs!$B$32 -> 0 | F30: =Inputs!$B$32 -> 0 | G30: =Inputs!$B$32 -> 0 | H30: =Inputs!$B$32 -> 0 | I30: =Inputs!$B$32 -> 0 | J30: =Inputs!$B$32 -> 0 | ... AL30: =Inputs!$B$32 -> 0
A31: Marketing: paid acquisition | C31: =Inputs!$C$37 -> 300 | D31: =Inputs!$C$37 -> 300 | E31: =Inputs!$C$37 -> 300 | F31: =Inputs!$C$37 -> 300 | G31: =Inputs!$C$37 -> 300 | H31: =Inputs!$C$37 -> 300 | I31: =Inputs!$C$37 -> 300 | J31: =Inputs!$C$37 -> 300 | ... AL31: =Inputs!$C$37 -> 300
A32: Marketing: gatherings | C32: =Inputs!$C$39*Inputs!$C$40 -> 300 | D32: =Inputs!$C$39*Inputs!$C$40 -> 300 | E32: =Inputs!$C$39*Inputs!$C$40 -> 300 | F32: =Inputs!$C$39*Inputs!$C$40 -> 300 | G32: =Inputs!$C$39*Inputs!$C$40 -> 300 | H32: =Inputs!$C$39*Inputs!$C$40 -> 300 | I32: =Inputs!$C$39*Inputs!$C$40 -> 300 | J32: =Inputs!$C$39*Inputs!$C$40 -> 300 | ... AL32: =Inputs!$C$39*Inputs!$C$40 -> 300
A33: Marketing: content and tools | C33: =Inputs!$C$41 -> 100 | D33: =Inputs!$C$41 -> 100 | E33: =Inputs!$C$41 -> 100 | F33: =Inputs!$C$41 -> 100 | G33: =Inputs!$C$41 -> 100 | H33: =Inputs!$C$41 -> 100 | I33: =Inputs!$C$41 -> 100 | J33: =Inputs!$C$41 -> 100 | ... AL33: =Inputs!$C$41 -> 100
A34: Marketing: November 6 and the film series | C34: =Inputs!$C$42 -> 3000 | D34: =0 -> 0 | E34: =Inputs!$C$43 -> 0 | F34: =0 -> 0 | G34: =0 -> 0 | H34: =0 -> 0 | I34: =0 -> 0 | J34: =0 -> 0 | K34: =0 -> 0 | L34: =0 -> 0 | M34: =0 -> 0 | ... AL34: =0 -> 0
A35: TOTAL COSTS BEFORE FOUNDERS | C35: =SUM(C26:C34) -> 4693.805 | D35: =SUM(D26:D34) -> 1004.7691 | E35: =SUM(E26:E34) -> 1015.5771 | F35: =SUM(F26:F34) -> 1026.2336 | G35: =SUM(G26:G34) -> 2286.7432 | H35: =SUM(H26:H34) -> 1047.1103 | I35: =SUM(I26:I34) -> 1057.3393 | J35: =SUM(J26:J34) -> 1067.4341 | ... AL35: =SUM(AL26:AL34) -> 1309.1387
A36: of which marketing | C36: =SUM(C31:C34) -> 3700 | D36: =SUM(D31:D34) -> 700 | E36: =SUM(E31:E34) -> 700 | F36: =SUM(F31:F34) -> 700 | G36: =SUM(G31:G34) -> 700 | H36: =SUM(H31:H34) -> 700 | I36: =SUM(I31:I34) -> 700 | J36: =SUM(J31:J34) -> 700 | ... AL36: =SUM(AL31:AL34) -> 700
A38: CASH
A39: Operating cash flow (revenue less costs) | C39: =C23-C35 -> -795.32503 | D39: =D23-D35 -> 1063.4965 | E39: =E23-E35 -> 1217.9206 | F39: =F23-F35 -> 1368.0791 | G39: =G23-G35 -> 264.10012 | H39: =H23-H35 -> 1656.1077 | I39: =I23-I35 -> 1794.2222 | J39: =J23-J35 -> 1928.5605 | ... AL39: =AL23-AL35 -> 7536.573
A40: Founder distributions (share of revenue once past the threshold) | C40: =IF(IF(Inputs!$B$8=1,C22,C23)>=Inputs!$B$6,C23*Inputs!$B$7,0) -> 0 | D40: =IF(IF(Inputs!$B$8=1,D22,D23)>=Inputs!$B$6,D23*Inputs!$B$7,0) -> 0 | E40: =IF(IF(Inputs!$B$8=1,E22,E23)>=Inputs!$B$6,E23*Inputs!$B$7,0) -> 0 | F40: =IF(IF(Inputs!$B$8=1,F22,F23)>=Inputs!$B$6,F23*Inputs!$B$7,0) -> 0 | G40: =IF(IF(Inputs!$B$8=1,G22,G23)>=Inputs!$B$6,G23*Inputs!$B$7,0) -> 765.253 | H40: =IF(IF(Inputs!$B$8=1,H22,H23)>=Inputs!$B$6,H23*Inputs!$B$7,0) -> 810.96541 | I40: =IF(IF(Inputs!$B$8=1,I22,I23)>=Inputs!$B$6,I23*Inputs!$B$7,0) -> 855.46844 | J40: =IF(IF(Inputs!$B$8=1,J22,J23)>=Inputs!$B$6,J23*Inputs!$B$7,0) -> 898.79839 | ... AL40: =IF(IF(Inputs!$B$8=1,AL22,AL23)>=Inputs!$B$6,AL23*Inputs!$B$7,0) -> 2653.7135
A41: per founder | C41: =C40/Inputs!$B$9 -> 0 | D41: =D40/Inputs!$B$9 -> 0 | E41: =E40/Inputs!$B$9 -> 0 | F41: =F40/Inputs!$B$9 -> 0 | G41: =G40/Inputs!$B$9 -> 382.6265 | H41: =H40/Inputs!$B$9 -> 405.4827 | I41: =I40/Inputs!$B$9 -> 427.73422 | J41: =J40/Inputs!$B$9 -> 449.3992 | ... AL41: =AL40/Inputs!$B$9 -> 1326.8568
A42: Net cash flow | C42: =C39-C40 -> -795.32503 | D42: =D39-D40 -> 1063.4965 | E42: =E39-E40 -> 1217.9206 | F42: =F39-F40 -> 1368.0791 | G42: =G39-G40 -> -501.15287 | H42: =H39-H40 -> 845.14228 | I42: =I39-I40 -> 938.75379 | J42: =J39-J40 -> 1029.7621 | ... AL42: =AL39-AL40 -> 4882.8595
A43: CASH, END OF MONTH | C43: =Inputs!$B$5+C42 -> 9204.675 | D43: =C43+D42 -> 10268.171 | E43: =D43+E42 -> 11486.092 | F43: =E43+F42 -> 12854.171 | G43: =F43+G42 -> 12353.018 | H43: =G43+H42 -> 13198.161 | I43: =H43+I42 -> 14136.914 | J43: =I43+J42 -> 15166.676 | K43: =J43+K42 -> 16284.922 | ... AL43: =AK43+AL42 -> 106186.47
A44: Cumulative founder draw, each | C44: =C41 -> 0 | D44: =C44+D41 -> 0 | E44: =D44+E41 -> 0 | F44: =E44+F41 -> 0 | G44: =F44+G41 -> 382.6265 | H44: =G44+H41 -> 788.1092 | I44: =H44+I41 -> 1215.8434 | J44: =I44+J41 -> 1665.2426 | K44: =J44+K41 -> 2135.7378 | ... AL44: =AK44+AL41 -> 29237.515

Sheet Push
A1: Push marketing level, monthly, months 1 to 36 (month 1 = November 2026)
A2: Month | C2: 1 | D2: 2 | E2: 3 | F2: 4 | G2: 5 | H2: 6 | I2: 7 | J2: 8 | K2: 9 | L2: 10 | M2: 11 | N2: 12 | O2: 13 | P2: 14 | Q2: 15 | R2: 16 | S2: 17 | T2: 18 | U2: 19 | V2: 20 | W2: 21 | X2: 22 | Y2: 23 | Z2: 24 | AA2: 25 | AB2: 26 | AC2: 27 | AD2: 28 | AE2: 29 | AF2: 30 | AG2: 31 | AH2: 32 | AI2: 33 | AJ2: 34 | AK2: 35 | AL2: 36
A3: Year | C3: 1 | D3: 1 | E3: 1 | F3: 1 | G3: 1 | H3: 1 | I3: 1 | J3: 1 | K3: 1 | L3: 1 | M3: 1 | N3: 1 | O3: 2 | P3: 2 | Q3: 2 | R3: 2 | S3: 2 | T3: 2 | U3: 2 | V3: 2 | W3: 2 | X3: 2 | Y3: 2 | Z3: 2 | AA3: 3 | AB3: 3 | AC3: 3 | AD3: 3 | AE3: 3 | AF3: 3 | AG3: 3 | AH3: 3 | AI3: 3 | AJ3: 3 | AK3: 3 | AL3: 3
A5: MEMBERS
A6: Paying individuals, start of month | C6: =Inputs!$B$12 -> 20 | D6: =C10 -> 56.066667 | E6: =D10 -> 91.051333 | F6: =E10 -> 124.98646 | G6: =F10 -> 157.90353 | H6: =G10 -> 189.83309 | I6: =H10 -> 220.80477 | J6: =I10 -> 250.84729 | K6: =J10 -> 279.98854 | ... AL6: =AK10 -> 808.22688
A7: Organic adds | C7: =Inputs!$D$36 -> 10 | D7: =Inputs!$D$36 -> 10 | E7: =Inputs!$D$36 -> 10 | F7: =Inputs!$D$36 -> 10 | G7: =Inputs!$D$36 -> 10 | H7: =Inputs!$D$36 -> 10 | I7: =Inputs!$D$36 -> 10 | J7: =Inputs!$D$36 -> 10 | ... AL7: =Inputs!$D$36 -> 10
A8: Paid adds (paid $ / cost per convert) | C8: =IF(Inputs!$D$38=0,0,Inputs!$D$37/Inputs!$D$38) -> 26.666667 | D8: =IF(Inputs!$D$38=0,0,Inputs!$D$37/Inputs!$D$38) -> 26.666667 | E8: =IF(Inputs!$D$38=0,0,Inputs!$D$37/Inputs!$D$38) -> 26.666667 | F8: =IF(Inputs!$D$38=0,0,Inputs!$D$37/Inputs!$D$38) -> 26.666667 | G8: =IF(Inputs!$D$38=0,0,Inputs!$D$37/Inputs!$D$38) -> 26.666667 | H8: =IF(Inputs!$D$38=0,0,Inputs!$D$37/Inputs!$D$38) -> 26.666667 | I8: =IF(Inputs!$D$38=0,0,Inputs!$D$37/Inputs!$D$38) -> 26.666667 | J8: =IF(Inputs!$D$38=0,0,Inputs!$D$37/Inputs!$D$38) -> 26.666667 | ... AL8: =IF(Inputs!$D$38=0,0,Inputs!$D$37/Inputs!$D$38) -> 26.666667
A9: Churned | C9: =-C6*Inputs!$B$14 -> -0.6 | D9: =-D6*Inputs!$B$14 -> -1.682 | E9: =-E6*Inputs!$B$14 -> -2.73154 | F9: =-F6*Inputs!$B$14 -> -3.7495938 | G9: =-G6*Inputs!$B$14 -> -4.737106 | H9: =-H6*Inputs!$B$14 -> -5.6949928 | I9: =-I6*Inputs!$B$14 -> -6.624143 | J9: =-J6*Inputs!$B$14 -> -7.5254187 | ... AL9: =-AL6*Inputs!$B$14 -> -24.246807
A10: Paying individuals, end of month | C10: =C6+C7+C8+C9 -> 56.066667 | D10: =D6+D7+D8+D9 -> 91.051333 | E10: =E6+E7+E8+E9 -> 124.98646 | F10: =F6+F7+F8+F9 -> 157.90353 | G10: =G6+G7+G8+G9 -> 189.83309 | H10: =H6+H7+H8+H9 -> 220.80477 | I10: =I6+I7+I8+I9 -> 250.84729 | J10: =J6+J7+J8+J9 -> 279.98854 | ... AL10: =AL6+AL7+AL8+AL9 -> 820.64674
A11: Organization packs sold, cumulative | C11: =Inputs!$D$44 -> 1 | D11: =C11+Inputs!$D$44 -> 2 | E11: =D11+Inputs!$D$44 -> 3 | F11: =E11+Inputs!$D$44 -> 4 | G11: =F11+Inputs!$D$44 -> 5 | H11: =G11+Inputs!$D$44 -> 6 | I11: =H11+Inputs!$D$44 -> 7 | J11: =I11+Inputs!$D$44 -> 8 | K11: =J11+Inputs!$D$44 -> 9 | ... AL11: =AK11+Inputs!$D$44 -> 36
A12: Organization seats active | C12: =C11*Inputs!$B$15 -> 30 | D12: =D11*Inputs!$B$15 -> 60 | E12: =E11*Inputs!$B$15 -> 90 | F12: =F11*Inputs!$B$15 -> 120 | G12: =G11*Inputs!$B$15 -> 150 | H12: =H11*Inputs!$B$15 -> 180 | I12: =I11*Inputs!$B$15 -> 210 | J12: =J11*Inputs!$B$15 -> 240 | ... AL12: =AL11*Inputs!$B$15 -> 1080
A13: Members (individuals + organization seats) | C13: =C10+C12 -> 86.066667 | D13: =D10+D12 -> 151.05133 | E13: =E10+E12 -> 214.98646 | F13: =F10+F12 -> 277.90353 | G13: =G10+G12 -> 339.83309 | H13: =H10+H12 -> 400.80477 | I13: =I10+I12 -> 460.84729 | J13: =J10+J12 -> 519.98854 | ... AL13: =AL10+AL12 -> 1900.6467
A15: REVENUE
A16: Individual seats | C16: =C10*Inputs!$B$13 -> 560.66667 | D16: =D10*Inputs!$B$13 -> 910.51333 | E16: =E10*Inputs!$B$13 -> 1249.8646 | F16: =F10*Inputs!$B$13 -> 1579.0353 | G16: =G10*Inputs!$B$13 -> 1898.3309 | H16: =H10*Inputs!$B$13 -> 2208.0477 | I16: =I10*Inputs!$B$13 -> 2508.4729 | J16: =J10*Inputs!$B$13 -> 2799.8854 | ... AL16: =AL10*Inputs!$B$13 -> 8206.4674
A17: Organization packs (cash at sale, renewals every 12 months) | C17: =Inputs!$D$44*Inputs!$B$15*Inputs!$B$16*1 -> 3000 | D17: =Inputs!$D$44*Inputs!$B$15*Inputs!$B$16*1 -> 3000 | E17: =Inputs!$D$44*Inputs!$B$15*Inputs!$B$16*1 -> 3000 | F17: =Inputs!$D$44*Inputs!$B$15*Inputs!$B$16*1 -> 3000 | G17: =Inputs!$D$44*Inputs!$B$15*Inputs!$B$16*1 -> 3000 | H17: =Inputs!$D$44*Inputs!$B$15*Inputs!$B$16*1 -> 3000 | I17: =Inputs!$D$44*Inputs!$B$15*Inputs!$B$16*1 -> 3000 | J17: =Inputs!$D$44*Inputs!$B$15*Inputs!$B$16*1 -> 3000 | ... N17: =Inputs!$D$44*Inputs!$B$15*Inputs!$B$16*1 -> 3000 | O17: =Inputs!$D$44*Inputs!$B$15*Inputs!$B$16*2 -> 6000 | P17: =Inputs!$D$44*Inputs!$B$15*Inputs!$B$16*2 -> 6000 | Q17: =Inputs!$D$44*Inputs!$B$15*Inputs!$B$16*2 -> 6000 | R17: =Inputs!$D$44*Inputs!$B$15*Inputs!$B$16*2 -> 6000 | S17: =Inputs!$D$44*Inputs!$B$15*Inputs!$B$16*2 -> 6000 | T17: =Inputs!$D$44*Inputs!$B$15*Inputs!$B$16*2 -> 6000 | U17: =Inputs!$D$44*Inputs!$B$15*Inputs!$B$16*2 -> 6000 | V17: =Inputs!$D$44*Inputs!$B$15*Inputs!$B$16*2 -> 6000 | ... Z17: =Inputs!$D$44*Inputs!$B$15*Inputs!$B$16*2 -> 6000 | AA17: =Inputs!$D$44*Inputs!$B$15*Inputs!$B$16*3 -> 9000 | AB17: =Inputs!$D$44*Inputs!$B$15*Inputs!$B$16*3 -> 9000 | AC17: =Inputs!$D$44*Inputs!$B$15*Inputs!$B$16*3 -> 9000 | AD17: =Inputs!$D$44*Inputs!$B$15*Inputs!$B$16*3 -> 9000 | AE17: =Inputs!$D$44*Inputs!$B$15*Inputs!$B$16*3 -> 9000 | AF17: =Inputs!$D$44*Inputs!$B$15*Inputs!$B$16*3 -> 9000 | AG17: =Inputs!$D$44*Inputs!$B$15*Inputs!$B$16*3 -> 9000 | AH17: =Inputs!$D$44*Inputs!$B$15*Inputs!$B$16*3 -> 9000 | ... AL17: =Inputs!$D$44*Inputs!$B$15*Inputs!$B$16*3 -> 9000
A18: Money moved (memo) | C18: =C13*Inputs!$B$17 -> 1032.8 | D18: =D13*Inputs!$B$17 -> 1812.616 | E18: =E13*Inputs!$B$17 -> 2579.8375 | F18: =F13*Inputs!$B$17 -> 3334.8424 | G18: =G13*Inputs!$B$17 -> 4077.9971 | H18: =H13*Inputs!$B$17 -> 4809.6572 | I18: =I13*Inputs!$B$17 -> 5530.1675 | J18: =J13*Inputs!$B$17 -> 6239.8625 | ... AL18: =AL13*Inputs!$B$17 -> 22807.761
A19: Platform share of money moved | C19: =C18*Inputs!$B$18 -> 103.28 | D19: =D18*Inputs!$B$18 -> 181.2616 | E19: =E18*Inputs!$B$18 -> 257.98375 | F19: =F18*Inputs!$B$18 -> 333.48424 | G19: =G18*Inputs!$B$18 -> 407.79971 | H19: =H18*Inputs!$B$18 -> 480.96572 | I19: =I18*Inputs!$B$18 -> 553.01675 | J19: =J18*Inputs!$B$18 -> 623.98625 | ... AL19: =AL18*Inputs!$B$18 -> 2280.7761
A20: Program administration fee | C20: =Inputs!$B$19*Inputs!$B$20 -> 0 | D20: =Inputs!$B$19*Inputs!$B$20 -> 0 | E20: =Inputs!$B$19*Inputs!$B$20 -> 0 | F20: =Inputs!$B$19*Inputs!$B$20 -> 0 | G20: =Inputs!$B$19*Inputs!$B$20 -> 0 | H20: =Inputs!$B$19*Inputs!$B$20 -> 0 | I20: =Inputs!$B$19*Inputs!$B$20 -> 0 | J20: =Inputs!$B$19*Inputs!$B$20 -> 0 | ... AL20: =Inputs!$B$19*Inputs!$B$20 -> 0
A21: Sponsorships | C21: =Inputs!$B$21 -> 2000 | D21: =0 -> 0 | E21: =0 -> 0 | F21: =0 -> 0 | G21: =0 -> 0 | H21: =0 -> 0 | I21: =Inputs!$B$22/12 -> 0 | J21: =Inputs!$B$22/12 -> 0 | K21: =Inputs!$B$22/12 -> 0 | L21: =Inputs!$B$22/12 -> 0 | M21: =Inputs!$B$22/12 -> 0 | N21: =Inputs!$B$22/12 -> 0 | O21: =Inputs!$B$22/12 -> 0 | P21: =Inputs!$B$22/12 -> 0 | ... AL21: =Inputs!$B$22/12 -> 0
A22: Recurring revenue (memo: seats + share of money moved + program fee) | C22: =C16+C19+C20 -> 663.94667 | D22: =D16+D19+D20 -> 1091.7749 | E22: =E16+E19+E20 -> 1507.8484 | F22: =F16+F19+F20 -> 1912.5196 | G22: =G16+G19+G20 -> 2306.1306 | H22: =H16+H19+H20 -> 2689.0134 | I22: =I16+I19+I20 -> 3061.4897 | J22: =J16+J19+J20 -> 3423.8716 | ... AL22: =AL16+AL19+AL20 -> 10487.244
A23: TOTAL REVENUE | C23: =C16+C17+C19+C20+C21 -> 5663.9467 | D23: =D16+D17+D19+D20+D21 -> 4091.7749 | E23: =E16+E17+E19+E20+E21 -> 4507.8484 | F23: =F16+F17+F19+F20+F21 -> 4912.5196 | G23: =G16+G17+G19+G20+G21 -> 5306.1306 | H23: =H16+H17+H19+H20+H21 -> 5689.0134 | I23: =I16+I17+I19+I20+I21 -> 6061.4897 | J23: =J16+J17+J19+J20+J21 -> 6423.8716 | ... AL23: =AL16+AL17+AL19+AL20+AL21 -> 19487.244
A25: COSTS BEFORE FOUNDERS
A26: Hosting and tools | C26: =Inputs!$B$25 -> 150 | D26: =Inputs!$B$25 -> 150 | E26: =Inputs!$B$25 -> 150 | F26: =Inputs!$B$25 -> 150 | G26: =Inputs!$B$25 -> 150 | H26: =Inputs!$B$25 -> 150 | I26: =Inputs!$B$25 -> 150 | J26: =Inputs!$B$25 -> 150 | ... AL26: =Inputs!$B$25 -> 150
A27: Payment processing | C27: =C18*Inputs!$B$26 -> 33.0496 | D27: =D18*Inputs!$B$26 -> 58.003712 | E27: =E18*Inputs!$B$26 -> 82.554801 | F27: =F18*Inputs!$B$26 -> 106.71496 | G27: =G18*Inputs!$B$26 -> 130.49591 | H27: =H18*Inputs!$B$26 -> 153.90903 | I27: =I18*Inputs!$B$26 -> 176.96536 | J27: =J18*Inputs!$B$26 -> 199.6756 | ... AL27: =AL18*Inputs!$B$26 -> 729.84835
A28: Bookkeeping and insurance | C28: =Inputs!$B$27 -> 125 | D28: =Inputs!$B$27 -> 125 | E28: =Inputs!$B$27 -> 125 | F28: =Inputs!$B$27 -> 125 | G28: =Inputs!$B$27 -> 125 | H28: =Inputs!$B$27 -> 125 | I28: =Inputs!$B$27 -> 125 | J28: =Inputs!$B$27 -> 125 | ... AL28: =Inputs!$B$27 -> 125
A29: Formation, franchise taxes, tax return | C29: =Inputs!$B$28 -> 700 | D29: =0 -> 0 | E29: =0 -> 0 | F29: =0 -> 0 | G29: =Inputs!$B$29+Inputs!$B$31 -> 1250 | H29: =0 -> 0 | I29: =0 -> 0 | J29: =0 -> 0 | K29: =0 -> 0 | L29: =0 -> 0 | M29: =0 -> 0 | N29: =0 -> 0 | O29: =Inputs!$B$30 -> 800 | P29: =0 -> 0 | Q29: =0 -> 0 | R29: =0 -> 0 | S29: =Inputs!$B$29+Inputs!$B$31 -> 1250 | T29: =0 -> 0 | U29: =0 -> 0 | V29: =0 -> 0 | W29: =0 -> 0 | X29: =0 -> 0 | Y29: =0 -> 0 | Z29: =0 -> 0 | AA29: =Inputs!$B$30 -> 800 | AB29: =0 -> 0 | AC29: =0 -> 0 | AD29: =0 -> 0 | AE29: =Inputs!$B$29+Inputs!$B$31 -> 1250 | AF29: =0 -> 0 | AG29: =0 -> 0 | AH29: =0 -> 0 | AI29: =0 -> 0 | AJ29: =0 -> 0 | AK29: =0 -> 0 | AL29: =0 -> 0
A30: Contractors | C30: =Inputs!$B$32 -> 0 | D30: =Inputs!$B$32 -> 0 | E30: =Inputs!$B$32 -> 0 | F30: =Inputs!$B$32 -> 0 | G30: =Inputs!$B$32 -> 0 | H30: =Inputs!$B$32 -> 0 | I30: =Inputs!$B$32 -> 0 | J30: =Inputs!$B$32 -> 0 | ... AL30: =Inputs!$B$32 -> 0
A31: Marketing: paid acquisition | C31: =Inputs!$D$37 -> 800 | D31: =Inputs!$D$37 -> 800 | E31: =Inputs!$D$37 -> 800 | F31: =Inputs!$D$37 -> 800 | G31: =Inputs!$D$37 -> 800 | H31: =Inputs!$D$37 -> 800 | I31: =Inputs!$D$37 -> 800 | J31: =Inputs!$D$37 -> 800 | ... AL31: =Inputs!$D$37 -> 800
A32: Marketing: gatherings | C32: =Inputs!$D$39*Inputs!$D$40 -> 450 | D32: =Inputs!$D$39*Inputs!$D$40 -> 450 | E32: =Inputs!$D$39*Inputs!$D$40 -> 450 | F32: =Inputs!$D$39*Inputs!$D$40 -> 450 | G32: =Inputs!$D$39*Inputs!$D$40 -> 450 | H32: =Inputs!$D$39*Inputs!$D$40 -> 450 | I32: =Inputs!$D$39*Inputs!$D$40 -> 450 | J32: =Inputs!$D$39*Inputs!$D$40 -> 450 | ... AL32: =Inputs!$D$39*Inputs!$D$40 -> 450
A33: Marketing: content and tools | C33: =Inputs!$D$41 -> 300 | D33: =Inputs!$D$41 -> 300 | E33: =Inputs!$D$41 -> 300 | F33: =Inputs!$D$41 -> 300 | G33: =Inputs!$D$41 -> 300 | H33: =Inputs!$D$41 -> 300 | I33: =Inputs!$D$41 -> 300 | J33: =Inputs!$D$41 -> 300 | ... AL33: =Inputs!$D$41 -> 300
A34: Marketing: November 6 and the film series | C34: =Inputs!$D$42 -> 6000 | D34: =0 -> 0 | E34: =Inputs!$D$43 -> 3000 | F34: =0 -> 0 | G34: =0 -> 0 | H34: =0 -> 0 | I34: =0 -> 0 | J34: =0 -> 0 | K34: =0 -> 0 | L34: =0 -> 0 | M34: =0 -> 0 | ... AL34: =0 -> 0
A35: TOTAL COSTS BEFORE FOUNDERS | C35: =SUM(C26:C34) -> 8558.0496 | D35: =SUM(D26:D34) -> 1883.0037 | E35: =SUM(E26:E34) -> 4907.5548 | F35: =SUM(F26:F34) -> 1931.715 | G35: =SUM(G26:G34) -> 3205.4959 | H35: =SUM(H26:H34) -> 1978.909 | I35: =SUM(I26:I34) -> 2001.9654 | J35: =SUM(J26:J34) -> 2024.6756 | ... AL35: =SUM(AL26:AL34) -> 2554.8483
A36: of which marketing | C36: =SUM(C31:C34) -> 7550 | D36: =SUM(D31:D34) -> 1550 | E36: =SUM(E31:E34) -> 4550 | F36: =SUM(F31:F34) -> 1550 | G36: =SUM(G31:G34) -> 1550 | H36: =SUM(H31:H34) -> 1550 | I36: =SUM(I31:I34) -> 1550 | J36: =SUM(J31:J34) -> 1550 | ... AL36: =SUM(AL31:AL34) -> 1550
A38: CASH
A39: Operating cash flow (revenue less costs) | C39: =C23-C35 -> -2894.1029 | D39: =D23-D35 -> 2208.7712 | E39: =E23-E35 -> -399.70645 | F39: =F23-F35 -> 2980.8046 | G39: =G23-G35 -> 2100.6347 | H39: =H23-H35 -> 3710.1044 | I39: =I23-I35 -> 4059.5243 | J39: =J23-J35 -> 4399.196 | ... AL39: =AL23-AL35 -> 16932.395
A40: Founder distributions (share of revenue once past the threshold) | C40: =IF(IF(Inputs!$B$8=1,C22,C23)>=Inputs!$B$6,C23*Inputs!$B$7,0) -> 0 | D40: =IF(IF(Inputs!$B$8=1,D22,D23)>=Inputs!$B$6,D23*Inputs!$B$7,0) -> 1227.5325 | E40: =IF(IF(Inputs!$B$8=1,E22,E23)>=Inputs!$B$6,E23*Inputs!$B$7,0) -> 1352.3545 | F40: =IF(IF(Inputs!$B$8=1,F22,F23)>=Inputs!$B$6,F23*Inputs!$B$7,0) -> 1473.7559 | G40: =IF(IF(Inputs!$B$8=1,G22,G23)>=Inputs!$B$6,G23*Inputs!$B$7,0) -> 1591.8392 | H40: =IF(IF(Inputs!$B$8=1,H22,H23)>=Inputs!$B$6,H23*Inputs!$B$7,0) -> 1706.704 | I40: =IF(IF(Inputs!$B$8=1,I22,I23)>=Inputs!$B$6,I23*Inputs!$B$7,0) -> 1818.4469 | J40: =IF(IF(Inputs!$B$8=1,J22,J23)>=Inputs!$B$6,J23*Inputs!$B$7,0) -> 1927.1615 | ... AL40: =IF(IF(Inputs!$B$8=1,AL22,AL23)>=Inputs!$B$6,AL23*Inputs!$B$7,0) -> 5846.1731
A41: per founder | C41: =C40/Inputs!$B$9 -> 0 | D41: =D40/Inputs!$B$9 -> 613.76624 | E41: =E40/Inputs!$B$9 -> 676.17725 | F41: =F40/Inputs!$B$9 -> 736.87794 | G41: =G40/Inputs!$B$9 -> 795.9196 | H41: =H40/Inputs!$B$9 -> 853.35201 | I41: =I40/Inputs!$B$9 -> 909.22345 | J41: =J40/Inputs!$B$9 -> 963.58075 | ... AL41: =AL40/Inputs!$B$9 -> 2923.0865
A42: Net cash flow | C42: =C39-C40 -> -2894.1029 | D42: =D39-D40 -> 981.23874 | E42: =E39-E40 -> -1752.061 | F42: =F39-F40 -> 1507.0487 | G42: =G39-G40 -> 508.79555 | H42: =H39-H40 -> 2003.4003 | I42: =I39-I40 -> 2241.0774 | J42: =J39-J40 -> 2472.0345 | ... AL42: =AL39-AL40 -> 11086.222
A43: CASH, END OF MONTH | C43: =Inputs!$B$5+C42 -> 7105.8971 | D43: =C43+D42 -> 8087.1358 | E43: =D43+E42 -> 6335.0749 | F43: =E43+F42 -> 7842.1236 | G43: =F43+G42 -> 8350.9191 | H43: =G43+H42 -> 10354.319 | I43: =H43+I42 -> 12595.397 | J43: =I43+J42 -> 15067.431 | K43: =J43+K42 -> 17763.905 | ... AL43: =AK43+AL42 -> 227706.28
A44: Cumulative founder draw, each | C44: =C41 -> 0 | D44: =C44+D41 -> 613.76624 | E44: =D44+E41 -> 1289.9435 | F44: =E44+F41 -> 2026.8214 | G44: =F44+G41 -> 2822.741 | H44: =G44+H41 -> 3676.093 | I44: =H44+I41 -> 4585.3165 | J44: =I44+J41 -> 5548.8972 | K44: =J44+K41 -> 6565.3666 | ... AL44: =AK44+AL41 -> 65875.677
