Workbook

Sheet Assumptions
A1: The Garden — P&L Model Assumptions
A2: Blue cells = inputs you can edit. Yellow fill = key levers. All $ figures are annual USD.
A4: Global levers
A5: Membership allocation — Space operations | B5: 0.4
A6: Membership allocation — creative project pool | B6: 0.5
A7: Membership allocation — platform (incl. processing) | B7: 0.1
A8: Platform share of all patronage flow (incl. processing) | B8: 0.1
A9: Payment processing cost (% of gross flow, paid from platform share) | B9: 0.03
A10: Average setup investment per new Space | B10: 3000
A11: Average Founding Patron partnership ($/yr) | B11: 15000
A13: Source: the-exchange-vision.md v0.10 Part 8 (40/50/10 membership split; 10% flow share; pilot tiers $10/$25/$50 + whole-church by quote). All figures are planning assumptions from Rick, not market data.
A15: Annual drivers by case
B16: Fnd Y1 | C16: Fnd Y2 | D16: Fnd Y3 | E16: Str Y1 | F16: Str Y2 | G16: Str Y3
A17: New Spaces onboarded | B17: 4 | C17: 3 | D17: 5 | E17: 6 | F17: 6 | G17: 8
A18: Gross membership dues ($/yr) | B18: 30000 | C18: 90000 | D18: 250000 | E18: 80000 | F18: 220000 | G18: 550000
A19: Gross patronage flow — Fellowships, Projects, seats ($/yr) | B19: 50000 | C19: 160000 | D19: 450000 | E19: 140000 | F19: 380000 | G19: 950000
A20: Founding Patron partnerships (count) | B20: 1 | C20: 2 | D20: 3 | E20: 3 | F20: 6 | G20: 10
A21: Showcase & event sponsorship revenue ($/yr) | B21: 8000 | C21: 15000 | D21: 25000 | E21: 15000 | F21: 25000 | G21: 40000
A23: Dues + patronage for Fnd Y1 sum to the vision doc's ~$80k total flow; Str Y1 to ~$220k; Y2–Y3 follow the trajectory table. Recalibrate after the pilot establishes real membership price, mix, and retention.
A25: Operating cost inputs ($/yr)
B26: Fnd Y1 | C26: Fnd Y2 | D26: Fnd Y3 | E26: Str Y1 | F26: Str Y2 | G26: Str Y3
A27: Infrastructure & hosting | B27: 3600 | C27: 6000 | D27: 10000 | E27: 4800 | F27: 9000 | G27: 15000
A28: Software & tools | B28: 2400 | C28: 3000 | D28: 4000 | E28: 2400 | F28: 3600 | G28: 5000
A29: Contractors (design / eng / ops) | B29: 5000 | C29: 15000 | D29: 30000 | E29: 10000 | F29: 30000 | G29: 60000
A30: Marketing & showcase production | B30: 3000 | C30: 5000 | D30: 8000 | E30: 5000 | F30: 8000 | G30: 12000
A31: Legal, accounting & insurance | B31: 2000 | C31: 3000 | D31: 5000 | E31: 3000 | F31: 5000 | G31: 8000
A33: Cost inputs are Rick's planning estimates. No founder salary included — see P&L memo.

Sheet P&L
A1: The Garden — 3-Year P&L (Foundation & Stretch)
A2: All cells on this sheet are formulas driven by the Assumptions tab. Edit inputs there (blue cells).
B4: Fnd Y1 | C4: Fnd Y2 | D4: Fnd Y3 | E4: Str Y1 | F4: Str Y2 | G4: Str Y3
A5: Revenue
A6: Platform share of membership dues (10%) | B6: =Assumptions!$B$7*Assumptions!B18 | C6: =Assumptions!$B$7*Assumptions!C18 | D6: =Assumptions!$B$7*Assumptions!D18 | E6: =Assumptions!$B$7*Assumptions!E18 | F6: =Assumptions!$B$7*Assumptions!F18 | G6: =Assumptions!$B$7*Assumptions!G18
A7: Platform share of patronage flow (10%) | B7: =Assumptions!$B$8*Assumptions!B19 | C7: =Assumptions!$B$8*Assumptions!C19 | D7: =Assumptions!$B$8*Assumptions!D19 | E7: =Assumptions!$B$8*Assumptions!E19 | F7: =Assumptions!$B$8*Assumptions!F19 | G7: =Assumptions!$B$8*Assumptions!G19
A8: Less: payment processing (3% of gross flow) | B8: =-Assumptions!$B$9*(Assumptions!B18+Assumptions!B19) | C8: =-Assumptions!$B$9*(Assumptions!C18+Assumptions!C19) | D8: =-Assumptions!$B$9*(Assumptions!D18+Assumptions!D19) | E8: =-Assumptions!$B$9*(Assumptions!E18+Assumptions!E19) | F8: =-Assumptions!$B$9*(Assumptions!F18+Assumptions!F19) | G8: =-Assumptions!$B$9*(Assumptions!G18+Assumptions!G19)
A9: Net platform flow revenue | B9: =SUM(B6:B8) | C9: =SUM(C6:C8) | D9: =SUM(D6:D8) | E9: =SUM(E6:E8) | F9: =SUM(F6:F8) | G9: =SUM(G6:G8)
A10: Setup investments | B10: =Assumptions!$B$10*Assumptions!B17 | C10: =Assumptions!$B$10*Assumptions!C17 | D10: =Assumptions!$B$10*Assumptions!D17 | E10: =Assumptions!$B$10*Assumptions!E17 | F10: =Assumptions!$B$10*Assumptions!F17 | G10: =Assumptions!$B$10*Assumptions!G17
A11: Founding Patron partnerships | B11: =Assumptions!$B$11*Assumptions!B20 | C11: =Assumptions!$B$11*Assumptions!C20 | D11: =Assumptions!$B$11*Assumptions!D20 | E11: =Assumptions!$B$11*Assumptions!E20 | F11: =Assumptions!$B$11*Assumptions!F20 | G11: =Assumptions!$B$11*Assumptions!G20
A12: Showcase & event sponsorships | B12: =Assumptions!B21 | C12: =Assumptions!C21 | D12: =Assumptions!D21 | E12: =Assumptions!E21 | F12: =Assumptions!F21 | G12: =Assumptions!G21
A13: Total revenue | B13: =B9+B10+B11+B12 | C13: =C9+C10+C11+C12 | D13: =D9+D10+D11+D12 | E13: =E9+E10+E11+E12 | F13: =F9+F10+F11+F12 | G13: =G9+G10+G11+G12
A15: Operating costs
A16: Infrastructure & hosting | B16: =Assumptions!B27 | C16: =Assumptions!C27 | D16: =Assumptions!D27 | E16: =Assumptions!E27 | F16: =Assumptions!F27 | G16: =Assumptions!G27
A17: Software & tools | B17: =Assumptions!B28 | C17: =Assumptions!C28 | D17: =Assumptions!D28 | E17: =Assumptions!E28 | F17: =Assumptions!F28 | G17: =Assumptions!G28
A18: Contractors (design / eng / ops) | B18: =Assumptions!B29 | C18: =Assumptions!C29 | D18: =Assumptions!D29 | E18: =Assumptions!E29 | F18: =Assumptions!F29 | G18: =Assumptions!G29
A19: Marketing & showcase production | B19: =Assumptions!B30 | C19: =Assumptions!C30 | D19: =Assumptions!D30 | E19: =Assumptions!E30 | F19: =Assumptions!F30 | G19: =Assumptions!G30
A20: Legal, accounting & insurance | B20: =Assumptions!B31 | C20: =Assumptions!C31 | D20: =Assumptions!D31 | E20: =Assumptions!E31 | F20: =Assumptions!F31 | G20: =Assumptions!G31
A21: Total operating costs | B21: =SUM(B16:B20) | C21: =SUM(C16:C20) | D21: =SUM(D16:D20) | E21: =SUM(E16:E20) | F21: =SUM(F16:F20) | G21: =SUM(G16:G20)
A23: Net income (before founder salary) | B23: =B13-B21 | C23: =C13-C21 | D23: =D13-D21 | E23: =E13-E21 | F23: =F13-F21 | G23: =G13-G21
A25: Memo — where the money goes
A26: Gross $ through platform | B26: =Assumptions!B18+Assumptions!B19 | C26: =Assumptions!C18+Assumptions!C19 | D26: =Assumptions!D18+Assumptions!D19 | E26: =Assumptions!E18+Assumptions!E19 | F26: =Assumptions!F18+Assumptions!F19 | G26: =Assumptions!G18+Assumptions!G19
A27: Creative project pool generated (50% of dues) | B27: =Assumptions!$B$6*Assumptions!B18 | C27: =Assumptions!$B$6*Assumptions!C18 | D27: =Assumptions!$B$6*Assumptions!D18 | E27: =Assumptions!$B$6*Assumptions!E18 | F27: =Assumptions!$B$6*Assumptions!F18 | G27: =Assumptions!$B$6*Assumptions!G18
A28: Space operations share (40% of dues) | B28: =Assumptions!$B$5*Assumptions!B18 | C28: =Assumptions!$B$5*Assumptions!C18 | D28: =Assumptions!$B$5*Assumptions!D18 | E28: =Assumptions!$B$5*Assumptions!E18 | F28: =Assumptions!$B$5*Assumptions!F18 | G28: =Assumptions!$B$5*Assumptions!G18
A29: Reaching creatives from patronage (90%) | B29: =(1-Assumptions!$B$8)*Assumptions!B19 | C29: =(1-Assumptions!$B$8)*Assumptions!C19 | D29: =(1-Assumptions!$B$8)*Assumptions!D19 | E29: =(1-Assumptions!$B$8)*Assumptions!E19 | F29: =(1-Assumptions!$B$8)*Assumptions!F19 | G29: =(1-Assumptions!$B$8)*Assumptions!G19
A31: Note: no founder salary is modeled. Net income is what's available for founder draw + reinvestment. Reconciles to the-exchange-vision.md v0.10 Part 8.
